{"resourceType":"Bundle","type":"transaction","entry":[{"fullUrl":"Patient/c68c1c0f-8fc6-42e6-a88e-a1dee7be3813","resource":{"resourceType":"Patient","id":"c68c1c0f-8fc6-42e6-a88e-a1dee7be3813","meta":{"profile":["http://hl7.org/fhir/us/core/StructureDefinition/us-core-patient"]},"text":{"status":"generated","div":"<div xmlns=\"http://www.w3.org/1999/xhtml\">Generated by <a href=\"https://github.com/synthetichealth/synthea\">Synthea</a>.Version identifier: v2.4.0-876-ge3e344b2\n .   Person seed: -8241970476479942587  Population seed: 1620845753740</div>"},"extension":[{"url":"http://hl7.org/fhir/us/core/StructureDefinition/us-core-race","extension":[{"url":"ombCategory","valueCoding":{"system":"urn:oid:2.16.840.1.113883.6.238","code":"2106-3","display":"White"}},{"url":"text","valueString":"White"}]},{"url":"http://hl7.org/fhir/us/core/StructureDefinition/us-core-ethnicity","extension":[{"url":"ombCategory","valueCoding":{"system":"urn:oid:2.16.840.1.113883.6.238","code":"2135-2","display":"Hispanic or Latino"}},{"url":"text","valueString":"Hispanic or Latino"}]},{"url":"http://hl7.org/fhir/StructureDefinition/patient-mothersMaidenName","valueString":"Trang668 Satterfield305"},{"url":"http://hl7.org/fhir/us/core/StructureDefinition/us-core-birthsex","valueCode":"M"},{"url":"http://hl7.org/fhir/StructureDefinition/patient-birthPlace","valueAddress":{"city":"Taunton","state":"Massachusetts","country":"US"}},{"url":"http://synthetichealth.github.io/synthea/disability-adjusted-life-years","valueDecimal":0},{"url":"http://synthetichealth.github.io/synthea/quality-adjusted-life-years","valueDecimal":19}],"identifier":[{"system":"https://github.com/synthetichealth/synthea","value":"c68c1c0f-8fc6-42e6-a88e-a1dee7be3813"},{"type":{"coding":[{"system":"http://terminology.hl7.org/CodeSystem/v2-0203","code":"MR","display":"Medical Record Number"}],"text":"Medical Record Number"},"system":"http://hospital.smarthealthit.org","value":"c68c1c0f-8fc6-42e6-a88e-a1dee7be3813"},{"type":{"coding":[{"system":"http://terminology.hl7.org/CodeSystem/v2-0203","code":"SS","display":"Social Security Number"}],"text":"Social Security Number"},"system":"http://hl7.org/fhir/sid/us-ssn","value":"999-59-8713"},{"type":{"coding":[{"system":"http://terminology.hl7.org/CodeSystem/v2-0203","code":"DL","display":"Driver's License"}],"text":"Driver's License"},"system":"urn:oid:2.16.840.1.113883.4.3.25","value":"S99946661"}],"name":[{"use":"official","family":"Rippin620","given":["Benito209"],"prefix":["Mr."]}],"telecom":[{"system":"phone","value":"555-777-1729","use":"home"}],"gender":"male","birthDate":"2002-01-02","address":[{"extension":[{"url":"http://hl7.org/fhir/StructureDefinition/geolocation","extension":[{"url":"latitude","valueDecimal":42.434250314488274},{"url":"longitude","valueDecimal":-70.98178415507894}]}],"line":["210 Kris Highlands"],"city":"Chelsea","state":"MA","postalCode":"02151","country":"US"}],"maritalStatus":{"coding":[{"system":"http://terminology.hl7.org/CodeSystem/v3-MaritalStatus","code":"S","display":"Never Married"}],"text":"Never Married"},"multipleBirthBoolean":false,"communication":[{"language":{"coding":[{"system":"urn:ietf:bcp:47","code":"en-US","display":"English"}],"text":"English"}}]},"request":{"method":"POST","url":"Patient"}},{"fullUrl":"Location/d8d6b15d-80b2-4fe6-8a69-ec76a4d613e2","resource":{"resourceType":"Location","id":"d8d6b15d-80b2-4fe6-8a69-ec76a4d613e2","meta":{"profile":["http://hl7.org/fhir/us/core/StructureDefinition/us-core-location"]},"identifier":[{"system":"https://github.com/synthetichealth/synthea","value":"c4375b9e-1f4a-4630-b749-52ceed708ed2"}],"status":"active","name":"PCP140496","telecom":[{"system":"phone","value":"(555) 555-5555"}],"address":{"line":["454 BROADWAY"],"city":"REVERE","state":"MA","postalCode":"02151-3050","country":"US"},"position":{"longitude":-70.99036,"latitude":42.421005},"managingOrganization":{"reference":"Organization/f28ce7cd-867f-3431-99e3-ab62ed072852","display":"PCP140496"}},"request":{"method":"POST","url":"Location"}},{"fullUrl":"Organization/f28ce7cd-867f-3431-99e3-ab62ed072852","resource":{"resourceType":"Organization","id":"f28ce7cd-867f-3431-99e3-ab62ed072852","meta":{"profile":["http://hl7.org/fhir/us/core/StructureDefinition/us-core-organization"]},"identifier":[{"system":"https://github.com/synthetichealth/synthea","value":"f28ce7cd-867f-3431-99e3-ab62ed072852"}],"active":true,"type":[{"coding":[{"system":"http://terminology.hl7.org/CodeSystem/organization-type","code":"prov","display":"Healthcare Provider"}],"text":"Healthcare Provider"}],"name":"PCP140496","telecom":[{"system":"phone","value":"(555) 555-5555"}],"address":[{"line":["454 BROADWAY"],"city":"REVERE","state":"MA","postalCode":"02151-3050","country":"US"}]},"request":{"method":"POST","url":"Organization"}},{"fullUrl":"Practitioner/a7f83620-8350-3d63-813e-627a56c3a05e","resource":{"resourceType":"Practitioner","id":"a7f83620-8350-3d63-813e-627a56c3a05e","meta":{"profile":["http://hl7.org/fhir/us/core/StructureDefinition/us-core-practitioner"]},"identifier":[{"system":"http://hl7.org/fhir/sid/us-npi","value":"9999949949"}],"active":true,"name":[{"family":"Lesch175","given":["Karlene380"],"prefix":["Dr."]}],"telecom":[{"extension":[{"url":"http://hl7.org/fhir/us/core/StructureDefinition/us-core-direct","valueBoolean":true}],"system":"email","value":"Karlene380.Lesch175@example.com","use":"work"}],"address":[{"line":["454 BROADWAY"],"city":"REVERE","state":"MA","postalCode":"02151-3050","country":"US"}],"gender":"female"},"request":{"method":"POST","url":"Practitioner"}},{"fullUrl":"PractitionerRole/641136fd-8ee2-462a-9062-bd5bfe6917e6","resource":{"resourceType":"PractitionerRole","id":"641136fd-8ee2-462a-9062-bd5bfe6917e6","meta":{"profile":["http://hl7.org/fhir/us/core/StructureDefinition/us-core-practitionerrole"]},"practitioner":{"reference":"Practitioner/a7f83620-8350-3d63-813e-627a56c3a05e","display":"Dr. Karlene380 Lesch175"},"organization":{"reference":"Organization/f28ce7cd-867f-3431-99e3-ab62ed072852","display":"PCP140496"},"code":[{"coding":[{"system":"http://nucc.org/provider-taxonomy","code":"208D00000X","display":"General Practice"}],"text":"General Practice"}],"specialty":[{"coding":[{"system":"http://nucc.org/provider-taxonomy","code":"208D00000X","display":"General Practice"}],"text":"General Practice"}],"location":[{"reference":"Location/d8d6b15d-80b2-4fe6-8a69-ec76a4d613e2","display":"PCP140496"}],"telecom":[{"extension":[{"url":"http://hl7.org/fhir/us/core/StructureDefinition/us-core-direct","valueBoolean":true}],"system":"email","value":"Karlene380.Lesch175@example.com","use":"work"}]},"request":{"method":"POST","url":"PractitionerRole"}},{"fullUrl":"Encounter/ed48c51b-3b76-4420-aed7-2e6c532dd668","resource":{"resourceType":"Encounter","id":"ed48c51b-3b76-4420-aed7-2e6c532dd668","meta":{"profile":["http://hl7.org/fhir/us/core/StructureDefinition/us-core-encounter"]},"identifier":[{"system":"https://github.com/synthetichealth/synthea","value":"20ef821e-7295-41ed-9292-b00dc3dbffe1"},{"use":"official","system":"https://github.com/synthetichealth/synthea","value":"ed48c51b-3b76-4420-aed7-2e6c532dd668"}],"status":"finished","class":{"system":"http://terminology.hl7.org/CodeSystem/v3-ActCode","code":"AMB"},"type":[{"coding":[{"system":"http://snomed.info/sct","code":"162673000","display":"General examination of patient (procedure)"}],"text":"General examination of patient (procedure)"}],"subject":{"reference":"Patient/c68c1c0f-8fc6-42e6-a88e-a1dee7be3813","display":"Mr. Benito209 Rippin620"},"participant":[{"type":[{"coding":[{"system":"http://terminology.hl7.org/CodeSystem/v3-ParticipationType","code":"PPRF","display":"primary performer"}],"text":"primary performer"}],"period":{"start":"2020-02-26T17:41:38-05:00","end":"2020-02-26T17:56:38-05:00"},"individual":{"reference":"Practitioner/a7f83620-8350-3d63-813e-627a56c3a05e","display":"Dr. Karlene380 Lesch175"}}],"period":{"start":"2020-02-26T17:41:38-05:00","end":"2020-02-26T17:56:38-05:00"},"location":[{"location":{"reference":"Location/d8d6b15d-80b2-4fe6-8a69-ec76a4d613e2","display":"PCP140496"}}],"serviceProvider":{"reference":"Organization/f28ce7cd-867f-3431-99e3-ab62ed072852","display":"PCP140496"}},"request":{"method":"POST","url":"Encounter"}},{"fullUrl":"Immunization/adc21063-a0aa-4099-80a1-bfbcc40fca10","resource":{"resourceType":"Immunization","id":"adc21063-a0aa-4099-80a1-bfbcc40fca10","meta":{"profile":["http://hl7.org/fhir/us/core/StructureDefinition/us-core-immunization"]},"identifier":[{"system":"https://github.com/synthetichealth/synthea","value":"f2bc1f46-0e68-4dc6-9f3d-9fb689e82592"}],"status":"completed","vaccineCode":{"coding":[{"system":"http://hl7.org/fhir/sid/cvx","code":"140","display":"Influenza, seasonal, injectable, preservative free"}],"text":"Influenza, seasonal, injectable, preservative free"},"patient":{"reference":"Patient/c68c1c0f-8fc6-42e6-a88e-a1dee7be3813"},"encounter":{"reference":"Encounter/ed48c51b-3b76-4420-aed7-2e6c532dd668"},"occurrenceDateTime":"2020-02-26T17:41:38-05:00","primarySource":true,"location":{"reference":"Location/d8d6b15d-80b2-4fe6-8a69-ec76a4d613e2","display":"PCP140496"}},"request":{"method":"POST","url":"Immunization"}},{"fullUrl":"DiagnosticReport/b436f367-56af-49ba-b99d-5c38491e6c0b","resource":{"resourceType":"DiagnosticReport","id":"b436f367-56af-49ba-b99d-5c38491e6c0b","meta":{"profile":["http://hl7.org/fhir/us/core/StructureDefinition/us-core-diagnosticreport-note"]},"identifier":[{"system":"https://github.com/synthetichealth/synthea","value":"9a3ebd43-12cf-4923-846e-b97d783d6b3d"}],"status":"final","category":[{"coding":[{"system":"http://loinc.org","code":"34117-2","display":"History and physical note"},{"system":"http://loinc.org","code":"51847-2","display":"Evaluation+Plan note"}]}],"code":{"coding":[{"system":"http://loinc.org","code":"34117-2","display":"History and physical note"},{"system":"http://loinc.org","code":"51847-2","display":"Evaluation+Plan note"}]},"subject":{"reference":"Patient/c68c1c0f-8fc6-42e6-a88e-a1dee7be3813"},"encounter":{"reference":"Encounter/ed48c51b-3b76-4420-aed7-2e6c532dd668"},"effectiveDateTime":"2020-02-26T17:41:38-05:00","issued":"2020-02-26T17:41:38.364-05:00","performer":[{"reference":"Practitioner/a7f83620-8350-3d63-813e-627a56c3a05e","display":"Dr. Karlene380 Lesch175"}],"presentedForm":[{"contentType":"text/plain","data":"CjIwMjAtMDItMjYKCiMgQ2hpZWYgQ29tcGxhaW50Ck5vIGNvbXBsYWludHMuCgojIEhpc3Rvcnkgb2YgUHJlc2VudCBJbGxuZXNzCkJlbml0bzIwOSBpcyBhIDE4IHllYXItb2xkIG5vbi1oaXNwYW5pYyB3aGl0ZSBtYWxlLgoKIyBTb2NpYWwgSGlzdG9yeQogUGF0aWVudCBpcyBhbiBhY3RpdmUgc21va2VyLiBQYXRpZW50IGlkZW50aWZpZXMgYXMgaGV0ZXJvc2V4dWFsLgoKUGF0aWVudCBjb21lcyBmcm9tIGEgbWlkZGxlIHNvY2lvZWNvbm9taWMgYmFja2dyb3VuZC4gUGF0aWVudCBkaWQgbm90IGZpbmlzaCBoaWdoIHNjaG9vbC4gUGF0aWVudCBjdXJyZW50bHkgaGFzIEh1bWFuYS4KCiMgQWxsZXJnaWVzCk5vIEtub3duIEFsbGVyZ2llcy4KCiMgTWVkaWNhdGlvbnMKTm8gQWN0aXZlIE1lZGljYXRpb25zLgoKIyBBc3Nlc3NtZW50IGFuZCBQbGFuCgoKIyMgUGxhbgpQYXRpZW50IHdhcyBnaXZlbiB0aGUgZm9sbG93aW5nIGltbXVuaXphdGlvbnM6IGluZmx1ZW56YSwgc2Vhc29uYWwsIGluamVjdGFibGUsIHByZXNlcnZhdGl2ZSBmcmVlLiAK"}]},"request":{"method":"POST","url":"DiagnosticReport"}},{"fullUrl":"DocumentReference/48d053b5-57aa-4166-adef-63394e8cd527","resource":{"resourceType":"DocumentReference","id":"48d053b5-57aa-4166-adef-63394e8cd527","meta":{"profile":["http://hl7.org/fhir/us/core/StructureDefinition/us-core-documentreference"]},"identifier":[{"system":"urn:ietf:rfc:3986","value":"b436f367-56af-49ba-b99d-5c38491e6c0b"}],"status":"superseded","type":{"coding":[{"system":"http://loinc.org","code":"34117-2","display":"History and physical note"},{"system":"http://loinc.org","code":"51847-2","display":"Evaluation+Plan note"}]},"category":[{"coding":[{"system":"http://hl7.org/fhir/us/core/CodeSystem/us-core-documentreference-category","code":"clinical-note","display":"Clinical Note"}]}],"subject":{"reference":"Patient/c68c1c0f-8fc6-42e6-a88e-a1dee7be3813"},"date":"2020-02-26T17:41:38.364-05:00","author":[{"reference":"Practitioner/a7f83620-8350-3d63-813e-627a56c3a05e","display":"Dr. Karlene380 Lesch175"}],"custodian":{"reference":"Organization/f28ce7cd-867f-3431-99e3-ab62ed072852","display":"PCP140496"},"content":[{"attachment":{"contentType":"text/plain","data":"CjIwMjAtMDItMjYKCiMgQ2hpZWYgQ29tcGxhaW50Ck5vIGNvbXBsYWludHMuCgojIEhpc3Rvcnkgb2YgUHJlc2VudCBJbGxuZXNzCkJlbml0bzIwOSBpcyBhIDE4IHllYXItb2xkIG5vbi1oaXNwYW5pYyB3aGl0ZSBtYWxlLgoKIyBTb2NpYWwgSGlzdG9yeQogUGF0aWVudCBpcyBhbiBhY3RpdmUgc21va2VyLiBQYXRpZW50IGlkZW50aWZpZXMgYXMgaGV0ZXJvc2V4dWFsLgoKUGF0aWVudCBjb21lcyBmcm9tIGEgbWlkZGxlIHNvY2lvZWNvbm9taWMgYmFja2dyb3VuZC4gUGF0aWVudCBkaWQgbm90IGZpbmlzaCBoaWdoIHNjaG9vbC4gUGF0aWVudCBjdXJyZW50bHkgaGFzIEh1bWFuYS4KCiMgQWxsZXJnaWVzCk5vIEtub3duIEFsbGVyZ2llcy4KCiMgTWVkaWNhdGlvbnMKTm8gQWN0aXZlIE1lZGljYXRpb25zLgoKIyBBc3Nlc3NtZW50IGFuZCBQbGFuCgoKIyMgUGxhbgpQYXRpZW50IHdhcyBnaXZlbiB0aGUgZm9sbG93aW5nIGltbXVuaXphdGlvbnM6IGluZmx1ZW56YSwgc2Vhc29uYWwsIGluamVjdGFibGUsIHByZXNlcnZhdGl2ZSBmcmVlLiAK"},"format":{"system":"http://ihe.net/fhir/ValueSet/IHE.FormatCode.codesystem","code":"urn:ihe:iti:xds:2017:mimeTypeSufficient","display":"mimeType Sufficient"}}],"context":{"encounter":[{"reference":"Encounter/ed48c51b-3b76-4420-aed7-2e6c532dd668"}],"period":{"start":"2020-02-26T17:41:38-05:00","end":"2020-02-26T17:56:38-05:00"}}},"request":{"method":"POST","url":"DocumentReference"}},{"fullUrl":"Claim/f1dac895-89d8-4d40-99a7-157c17c86ecf","resource":{"resourceType":"Claim","id":"f1dac895-89d8-4d40-99a7-157c17c86ecf","identifier":[{"system":"https://github.com/synthetichealth/synthea","value":"fd0ac091-e60f-45ef-b927-e81a806f7434"}],"status":"active","type":{"coding":[{"system":"http://terminology.hl7.org/CodeSystem/claim-type","code":"institutional"}]},"use":"claim","patient":{"reference":"Patient/c68c1c0f-8fc6-42e6-a88e-a1dee7be3813","display":"Benito209 Rippin620"},"billablePeriod":{"start":"2020-02-26T17:41:38-05:00","end":"2020-02-26T17:56:38-05:00"},"created":"2020-02-26T17:56:38-05:00","provider":{"reference":"Organization/f28ce7cd-867f-3431-99e3-ab62ed072852","display":"PCP140496"},"priority":{"coding":[{"system":"http://terminology.hl7.org/CodeSystem/processpriority","code":"normal"}]},"facility":{"reference":"Location/d8d6b15d-80b2-4fe6-8a69-ec76a4d613e2","display":"PCP140496"},"supportingInfo":[{"sequence":1,"category":{"coding":[{"system":"http://terminology.hl7.org/CodeSystem/claiminformationcategory","code":"info"}]},"valueReference":{"reference":"Immunization/adc21063-a0aa-4099-80a1-bfbcc40fca10"}}],"insurance":[{"sequence":1,"focal":true,"coverage":{"display":"Humana"}}],"item":[{"sequence":1,"productOrService":{"coding":[{"system":"http://snomed.info/sct","code":"162673000","display":"General examination of patient (procedure)"}],"text":"General examination of patient (procedure)"},"encounter":[{"reference":"Encounter/ed48c51b-3b76-4420-aed7-2e6c532dd668"}]},{"sequence":2,"informationSequence":[1],"productOrService":{"coding":[{"system":"http://hl7.org/fhir/sid/cvx","code":"140","display":"Influenza, seasonal, injectable, preservative free"}],"text":"Influenza, seasonal, injectable, preservative free"},"net":{"value":140.52,"currency":"USD"}}],"total":{"value":129.16,"currency":"USD"}},"request":{"method":"POST","url":"Claim"}},{"fullUrl":"ExplanationOfBenefit/bd461f1d-5b06-46c8-98f7-c56bab5846c3","resource":{"resourceType":"ExplanationOfBenefit","id":"bd461f1d-5b06-46c8-98f7-c56bab5846c3","contained":[{"resourceType":"ServiceRequest","id":"referral","status":"completed","intent":"order","subject":{"reference":"Patient/c68c1c0f-8fc6-42e6-a88e-a1dee7be3813"},"requester":{"reference":"Practitioner/a7f83620-8350-3d63-813e-627a56c3a05e"},"performer":[{"reference":"Practitioner/a7f83620-8350-3d63-813e-627a56c3a05e"}]},{"resourceType":"Coverage","id":"coverage","status":"active","type":{"text":"Humana"},"beneficiary":{"reference":"Patient/c68c1c0f-8fc6-42e6-a88e-a1dee7be3813"},"payor":[{"display":"Humana"}]}],"identifier":[{"system":"https://github.com/synthetichealth/synthea","value":"34c1aafa-1037-4f0a-937b-28b148d57d3b"},{"system":"https://bluebutton.cms.gov/resources/variables/clm_id","value":"f1dac895-89d8-4d40-99a7-157c17c86ecf"},{"system":"https://bluebutton.cms.gov/resources/identifier/claim-group","value":"99999999999"}],"status":"active","type":{"coding":[{"system":"http://terminology.hl7.org/CodeSystem/claim-type","code":"institutional"}]},"use":"claim","patient":{"reference":"Patient/c68c1c0f-8fc6-42e6-a88e-a1dee7be3813"},"billablePeriod":{"start":"2020-02-26T17:56:38-05:00","end":"2021-02-26T17:56:38-05:00"},"created":"2020-02-26T17:56:38-05:00","insurer":{"display":"Humana"},"provider":{"reference":"Practitioner/a7f83620-8350-3d63-813e-627a56c3a05e"},"referral":{"reference":"#referral"},"facility":{"reference":"Location/d8d6b15d-80b2-4fe6-8a69-ec76a4d613e2","display":"PCP140496"},"claim":{"reference":"Claim/f1dac895-89d8-4d40-99a7-157c17c86ecf"},"outcome":"complete","careTeam":[{"sequence":1,"provider":{"reference":"Practitioner/a7f83620-8350-3d63-813e-627a56c3a05e"},"role":{"coding":[{"system":"http://terminology.hl7.org/CodeSystem/claimcareteamrole","code":"primary","display":"Primary Care Practitioner"}]}}],"insurance":[{"focal":true,"coverage":{"reference":"#coverage","display":"Humana"}}],"item":[{"sequence":1,"category":{"coding":[{"system":"https://bluebutton.cms.gov/resources/variables/line_cms_type_srvc_cd","code":"1","display":"Medical care"}]},"productOrService":{"coding":[{"system":"http://snomed.info/sct","code":"162673000","display":"General examination of patient (procedure)"}],"text":"General examination of patient (procedure)"},"servicedPeriod":{"start":"2020-02-26T17:41:38-05:00","end":"2020-02-26T17:56:38-05:00"},"locationCodeableConcept":{"coding":[{"system":"http://terminology.hl7.org/CodeSystem/ex-serviceplace","code":"19","display":"Off Campus-Outpatient Hospital"}]},"encounter":[{"reference":"Encounter/ed48c51b-3b76-4420-aed7-2e6c532dd668"}]},{"sequence":2,"informationSequence":[1],"category":{"coding":[{"system":"https://bluebutton.cms.gov/resources/variables/line_cms_type_srvc_cd","code":"1","display":"Medical care"}]},"productOrService":{"coding":[{"system":"http://hl7.org/fhir/sid/cvx","code":"140","display":"Influenza, seasonal, injectable, preservative free"}],"text":"Influenza, seasonal, injectable, preservative free"},"servicedPeriod":{"start":"2020-02-26T17:41:38-05:00","end":"2020-02-26T17:56:38-05:00"},"locationCodeableConcept":{"coding":[{"system":"http://terminology.hl7.org/CodeSystem/ex-serviceplace","code":"19","display":"Off Campus-Outpatient Hospital"}]},"net":{"value":140.52,"currency":"USD"},"adjudication":[{"category":{"coding":[{"system":"https://bluebutton.cms.gov/resources/codesystem/adjudication","code":"https://bluebutton.cms.gov/resources/variables/line_coinsrnc_amt","display":"Line Beneficiary Coinsurance Amount"}]},"amount":{"value":28.104000000000003,"currency":"USD"}},{"category":{"coding":[{"system":"https://bluebutton.cms.gov/resources/codesystem/adjudication","code":"https://bluebutton.cms.gov/resources/variables/line_prvdr_pmt_amt","display":"Line Provider Payment Amount"}]},"amount":{"value":112.41600000000001,"currency":"USD"}},{"category":{"coding":[{"system":"https://bluebutton.cms.gov/resources/codesystem/adjudication","code":"https://bluebutton.cms.gov/resources/variables/line_sbmtd_chrg_amt","display":"Line Submitted Charge Amount"}]},"amount":{"value":140.52,"currency":"USD"}},{"category":{"coding":[{"system":"https://bluebutton.cms.gov/resources/codesystem/adjudication","code":"https://bluebutton.cms.gov/resources/variables/line_alowd_chrg_amt","display":"Line Allowed Charge Amount"}]},"amount":{"value":140.52,"currency":"USD"}},{"category":{"coding":[{"system":"https://bluebutton.cms.gov/resources/codesystem/adjudication","code":"https://bluebutton.cms.gov/resources/variables/line_bene_ptb_ddctbl_amt","display":"Line Beneficiary Part B Deductible Amount"}]},"amount":{"value":0,"currency":"USD"}},{"category":{"coding":[{"system":"https://bluebutton.cms.gov/resources/codesystem/adjudication","code":"https://bluebutton.cms.gov/resources/variables/line_prcsg_ind_cd","display":"Line Processing Indicator Code"}]}}]}],"total":[{"category":{"coding":[{"system":"http://terminology.hl7.org/CodeSystem/adjudication","code":"submitted","display":"Submitted Amount"}],"text":"Submitted Amount"},"amount":{"value":129.16,"currency":"USD"}}],"payment":{"amount":{"value":112.41600000000001,"currency":"USD"}}},"request":{"method":"POST","url":"ExplanationOfBenefit"}},{"fullUrl":"Encounter/fbede6f6-19d9-4540-8286-60ddf1a28293","resource":{"resourceType":"Encounter","id":"fbede6f6-19d9-4540-8286-60ddf1a28293","meta":{"profile":["http://hl7.org/fhir/us/core/StructureDefinition/us-core-encounter"]},"identifier":[{"system":"https://github.com/synthetichealth/synthea","value":"ebda1bc7-77e0-45f8-bd0d-af733d79e398"},{"use":"official","system":"https://github.com/synthetichealth/synthea","value":"fbede6f6-19d9-4540-8286-60ddf1a28293"}],"status":"finished","class":{"system":"http://terminology.hl7.org/CodeSystem/v3-ActCode","code":"AMB"},"type":[{"coding":[{"system":"http://snomed.info/sct","code":"162673000","display":"General examination of patient (procedure)"}],"text":"General examination of patient (procedure)"}],"subject":{"reference":"Patient/c68c1c0f-8fc6-42e6-a88e-a1dee7be3813","display":"Mr. Benito209 Rippin620"},"participant":[{"type":[{"coding":[{"system":"http://terminology.hl7.org/CodeSystem/v3-ParticipationType","code":"PPRF","display":"primary performer"}],"text":"primary performer"}],"period":{"start":"2021-03-03T17:41:38-05:00","end":"2021-03-03T17:56:38-05:00"},"individual":{"reference":"Practitioner/a7f83620-8350-3d63-813e-627a56c3a05e","display":"Dr. Karlene380 Lesch175"}}],"period":{"start":"2021-03-03T17:41:38-05:00","end":"2021-03-03T17:56:38-05:00"},"location":[{"location":{"reference":"Location/d8d6b15d-80b2-4fe6-8a69-ec76a4d613e2","display":"PCP140496"}}],"serviceProvider":{"reference":"Organization/f28ce7cd-867f-3431-99e3-ab62ed072852","display":"PCP140496"}},"request":{"method":"POST","url":"Encounter"}},{"fullUrl":"Immunization/587e4d6f-0dc9-446f-8b46-ac874794c824","resource":{"resourceType":"Immunization","id":"587e4d6f-0dc9-446f-8b46-ac874794c824","meta":{"profile":["http://hl7.org/fhir/us/core/StructureDefinition/us-core-immunization"]},"identifier":[{"system":"https://github.com/synthetichealth/synthea","value":"3ce26c5b-05e9-4feb-9aec-cf69bb64da6e"}],"status":"completed","vaccineCode":{"coding":[{"system":"http://hl7.org/fhir/sid/cvx","code":"140","display":"Influenza, seasonal, injectable, preservative free"}],"text":"Influenza, seasonal, injectable, preservative free"},"patient":{"reference":"Patient/c68c1c0f-8fc6-42e6-a88e-a1dee7be3813"},"encounter":{"reference":"Encounter/fbede6f6-19d9-4540-8286-60ddf1a28293"},"occurrenceDateTime":"2021-03-03T17:41:38-05:00","primarySource":true,"location":{"reference":"Location/d8d6b15d-80b2-4fe6-8a69-ec76a4d613e2","display":"PCP140496"}},"request":{"method":"POST","url":"Immunization"}},{"fullUrl":"DiagnosticReport/5b4cb522-c17f-4e01-9e60-7d451b07cb20","resource":{"resourceType":"DiagnosticReport","id":"5b4cb522-c17f-4e01-9e60-7d451b07cb20","meta":{"profile":["http://hl7.org/fhir/us/core/StructureDefinition/us-core-diagnosticreport-note"]},"identifier":[{"system":"https://github.com/synthetichealth/synthea","value":"be60e1ed-901b-4d3e-88af-7c773118cc25"}],"status":"final","category":[{"coding":[{"system":"http://loinc.org","code":"34117-2","display":"History and physical note"},{"system":"http://loinc.org","code":"51847-2","display":"Evaluation+Plan note"}]}],"code":{"coding":[{"system":"http://loinc.org","code":"34117-2","display":"History and physical note"},{"system":"http://loinc.org","code":"51847-2","display":"Evaluation+Plan note"}]},"subject":{"reference":"Patient/c68c1c0f-8fc6-42e6-a88e-a1dee7be3813"},"encounter":{"reference":"Encounter/fbede6f6-19d9-4540-8286-60ddf1a28293"},"effectiveDateTime":"2021-03-03T17:41:38-05:00","issued":"2021-03-03T17:41:38.364-05:00","performer":[{"reference":"Practitioner/a7f83620-8350-3d63-813e-627a56c3a05e","display":"Dr. Karlene380 Lesch175"}],"presentedForm":[{"contentType":"text/plain","data":"CjIwMjEtMDMtMDMKCiMgQ2hpZWYgQ29tcGxhaW50Ck5vIGNvbXBsYWludHMuCgojIEhpc3Rvcnkgb2YgUHJlc2VudCBJbGxuZXNzCkJlbml0bzIwOSBpcyBhIDE5IHllYXItb2xkIG5vbi1oaXNwYW5pYyB3aGl0ZSBtYWxlLgoKIyBTb2NpYWwgSGlzdG9yeQogUGF0aWVudCBpcyBhbiBhY3RpdmUgc21va2VyLiBQYXRpZW50IGlkZW50aWZpZXMgYXMgaGV0ZXJvc2V4dWFsLgoKUGF0aWVudCBjb21lcyBmcm9tIGEgbWlkZGxlIHNvY2lvZWNvbm9taWMgYmFja2dyb3VuZC4gUGF0aWVudCBkaWQgbm90IGZpbmlzaCBoaWdoIHNjaG9vbC4gUGF0aWVudCBjdXJyZW50bHkgaGFzIEh1bWFuYS4KCiMgQWxsZXJnaWVzCk5vIEtub3duIEFsbGVyZ2llcy4KCiMgTWVkaWNhdGlvbnMKTm8gQWN0aXZlIE1lZGljYXRpb25zLgoKIyBBc3Nlc3NtZW50IGFuZCBQbGFuCgoKIyMgUGxhbgpQYXRpZW50IHdhcyBnaXZlbiB0aGUgZm9sbG93aW5nIGltbXVuaXphdGlvbnM6IGluZmx1ZW56YSwgc2Vhc29uYWwsIGluamVjdGFibGUsIHByZXNlcnZhdGl2ZSBmcmVlLiAK"}]},"request":{"method":"POST","url":"DiagnosticReport"}},{"fullUrl":"DocumentReference/d7eae182-a3bd-4a00-8816-8f9d345fd1b2","resource":{"resourceType":"DocumentReference","id":"d7eae182-a3bd-4a00-8816-8f9d345fd1b2","meta":{"profile":["http://hl7.org/fhir/us/core/StructureDefinition/us-core-documentreference"]},"identifier":[{"system":"urn:ietf:rfc:3986","value":"5b4cb522-c17f-4e01-9e60-7d451b07cb20"}],"status":"current","type":{"coding":[{"system":"http://loinc.org","code":"34117-2","display":"History and physical note"},{"system":"http://loinc.org","code":"51847-2","display":"Evaluation+Plan note"}]},"category":[{"coding":[{"system":"http://hl7.org/fhir/us/core/CodeSystem/us-core-documentreference-category","code":"clinical-note","display":"Clinical Note"}]}],"subject":{"reference":"Patient/c68c1c0f-8fc6-42e6-a88e-a1dee7be3813"},"date":"2021-03-03T17:41:38.364-05:00","author":[{"reference":"Practitioner/a7f83620-8350-3d63-813e-627a56c3a05e","display":"Dr. Karlene380 Lesch175"}],"custodian":{"reference":"Organization/f28ce7cd-867f-3431-99e3-ab62ed072852","display":"PCP140496"},"content":[{"attachment":{"contentType":"text/plain","data":"CjIwMjEtMDMtMDMKCiMgQ2hpZWYgQ29tcGxhaW50Ck5vIGNvbXBsYWludHMuCgojIEhpc3Rvcnkgb2YgUHJlc2VudCBJbGxuZXNzCkJlbml0bzIwOSBpcyBhIDE5IHllYXItb2xkIG5vbi1oaXNwYW5pYyB3aGl0ZSBtYWxlLgoKIyBTb2NpYWwgSGlzdG9yeQogUGF0aWVudCBpcyBhbiBhY3RpdmUgc21va2VyLiBQYXRpZW50IGlkZW50aWZpZXMgYXMgaGV0ZXJvc2V4dWFsLgoKUGF0aWVudCBjb21lcyBmcm9tIGEgbWlkZGxlIHNvY2lvZWNvbm9taWMgYmFja2dyb3VuZC4gUGF0aWVudCBkaWQgbm90IGZpbmlzaCBoaWdoIHNjaG9vbC4gUGF0aWVudCBjdXJyZW50bHkgaGFzIEh1bWFuYS4KCiMgQWxsZXJnaWVzCk5vIEtub3duIEFsbGVyZ2llcy4KCiMgTWVkaWNhdGlvbnMKTm8gQWN0aXZlIE1lZGljYXRpb25zLgoKIyBBc3Nlc3NtZW50IGFuZCBQbGFuCgoKIyMgUGxhbgpQYXRpZW50IHdhcyBnaXZlbiB0aGUgZm9sbG93aW5nIGltbXVuaXphdGlvbnM6IGluZmx1ZW56YSwgc2Vhc29uYWwsIGluamVjdGFibGUsIHByZXNlcnZhdGl2ZSBmcmVlLiAK"},"format":{"system":"http://ihe.net/fhir/ValueSet/IHE.FormatCode.codesystem","code":"urn:ihe:iti:xds:2017:mimeTypeSufficient","display":"mimeType Sufficient"}}],"context":{"encounter":[{"reference":"Encounter/fbede6f6-19d9-4540-8286-60ddf1a28293"}],"period":{"start":"2021-03-03T17:41:38-05:00","end":"2021-03-03T17:56:38-05:00"}}},"request":{"method":"POST","url":"DocumentReference"}},{"fullUrl":"Claim/1c4ae217-ba4c-45aa-807b-0a52a05f74d2","resource":{"resourceType":"Claim","id":"1c4ae217-ba4c-45aa-807b-0a52a05f74d2","identifier":[{"system":"https://github.com/synthetichealth/synthea","value":"2d28d30a-de5d-4db0-b90f-af2769960653"}],"status":"active","type":{"coding":[{"system":"http://terminology.hl7.org/CodeSystem/claim-type","code":"institutional"}]},"use":"claim","patient":{"reference":"Patient/c68c1c0f-8fc6-42e6-a88e-a1dee7be3813","display":"Benito209 Rippin620"},"billablePeriod":{"start":"2021-03-03T17:41:38-05:00","end":"2021-03-03T17:56:38-05:00"},"created":"2021-03-03T17:56:38-05:00","provider":{"reference":"Organization/f28ce7cd-867f-3431-99e3-ab62ed072852","display":"PCP140496"},"priority":{"coding":[{"system":"http://terminology.hl7.org/CodeSystem/processpriority","code":"normal"}]},"facility":{"reference":"Location/d8d6b15d-80b2-4fe6-8a69-ec76a4d613e2","display":"PCP140496"},"supportingInfo":[{"sequence":1,"category":{"coding":[{"system":"http://terminology.hl7.org/CodeSystem/claiminformationcategory","code":"info"}]},"valueReference":{"reference":"Immunization/587e4d6f-0dc9-446f-8b46-ac874794c824"}}],"insurance":[{"sequence":1,"focal":true,"coverage":{"display":"Humana"}}],"item":[{"sequence":1,"productOrService":{"coding":[{"system":"http://snomed.info/sct","code":"162673000","display":"General examination of patient (procedure)"}],"text":"General examination of patient (procedure)"},"encounter":[{"reference":"Encounter/fbede6f6-19d9-4540-8286-60ddf1a28293"}]},{"sequence":2,"informationSequence":[1],"productOrService":{"coding":[{"system":"http://hl7.org/fhir/sid/cvx","code":"140","display":"Influenza, seasonal, injectable, preservative free"}],"text":"Influenza, seasonal, injectable, preservative free"},"net":{"value":140.52,"currency":"USD"}}],"total":{"value":129.16,"currency":"USD"}},"request":{"method":"POST","url":"Claim"}},{"fullUrl":"ExplanationOfBenefit/a594c933-349f-4702-bca0-d34aef0186a9","resource":{"resourceType":"ExplanationOfBenefit","id":"a594c933-349f-4702-bca0-d34aef0186a9","contained":[{"resourceType":"ServiceRequest","id":"referral","status":"completed","intent":"order","subject":{"reference":"Patient/c68c1c0f-8fc6-42e6-a88e-a1dee7be3813"},"requester":{"reference":"Practitioner/a7f83620-8350-3d63-813e-627a56c3a05e"},"performer":[{"reference":"Practitioner/a7f83620-8350-3d63-813e-627a56c3a05e"}]},{"resourceType":"Coverage","id":"coverage","status":"active","type":{"text":"Humana"},"beneficiary":{"reference":"Patient/c68c1c0f-8fc6-42e6-a88e-a1dee7be3813"},"payor":[{"display":"Humana"}]}],"identifier":[{"system":"https://github.com/synthetichealth/synthea","value":"c70f79f7-6734-4025-be13-deaaaa179b7f"},{"system":"https://bluebutton.cms.gov/resources/variables/clm_id","value":"1c4ae217-ba4c-45aa-807b-0a52a05f74d2"},{"system":"https://bluebutton.cms.gov/resources/identifier/claim-group","value":"99999999999"}],"status":"active","type":{"coding":[{"system":"http://terminology.hl7.org/CodeSystem/claim-type","code":"institutional"}]},"use":"claim","patient":{"reference":"Patient/c68c1c0f-8fc6-42e6-a88e-a1dee7be3813"},"billablePeriod":{"start":"2021-03-03T17:56:38-05:00","end":"2022-03-03T17:56:38-05:00"},"created":"2021-03-03T17:56:38-05:00","insurer":{"display":"Humana"},"provider":{"reference":"Practitioner/a7f83620-8350-3d63-813e-627a56c3a05e"},"referral":{"reference":"#referral"},"facility":{"reference":"Location/d8d6b15d-80b2-4fe6-8a69-ec76a4d613e2","display":"PCP140496"},"claim":{"reference":"Claim/1c4ae217-ba4c-45aa-807b-0a52a05f74d2"},"outcome":"complete","careTeam":[{"sequence":1,"provider":{"reference":"Practitioner/a7f83620-8350-3d63-813e-627a56c3a05e"},"role":{"coding":[{"system":"http://terminology.hl7.org/CodeSystem/claimcareteamrole","code":"primary","display":"Primary Care Practitioner"}]}}],"insurance":[{"focal":true,"coverage":{"reference":"#coverage","display":"Humana"}}],"item":[{"sequence":1,"category":{"coding":[{"system":"https://bluebutton.cms.gov/resources/variables/line_cms_type_srvc_cd","code":"1","display":"Medical care"}]},"productOrService":{"coding":[{"system":"http://snomed.info/sct","code":"162673000","display":"General examination of patient (procedure)"}],"text":"General examination of patient (procedure)"},"servicedPeriod":{"start":"2021-03-03T17:41:38-05:00","end":"2021-03-03T17:56:38-05:00"},"locationCodeableConcept":{"coding":[{"system":"http://terminology.hl7.org/CodeSystem/ex-serviceplace","code":"19","display":"Off Campus-Outpatient Hospital"}]},"encounter":[{"reference":"Encounter/fbede6f6-19d9-4540-8286-60ddf1a28293"}]},{"sequence":2,"informationSequence":[1],"category":{"coding":[{"system":"https://bluebutton.cms.gov/resources/variables/line_cms_type_srvc_cd","code":"1","display":"Medical care"}]},"productOrService":{"coding":[{"system":"http://hl7.org/fhir/sid/cvx","code":"140","display":"Influenza, seasonal, injectable, preservative free"}],"text":"Influenza, seasonal, injectable, preservative free"},"servicedPeriod":{"start":"2021-03-03T17:41:38-05:00","end":"2021-03-03T17:56:38-05:00"},"locationCodeableConcept":{"coding":[{"system":"http://terminology.hl7.org/CodeSystem/ex-serviceplace","code":"19","display":"Off Campus-Outpatient Hospital"}]},"net":{"value":140.52,"currency":"USD"},"adjudication":[{"category":{"coding":[{"system":"https://bluebutton.cms.gov/resources/codesystem/adjudication","code":"https://bluebutton.cms.gov/resources/variables/line_coinsrnc_amt","display":"Line Beneficiary Coinsurance Amount"}]},"amount":{"value":28.104000000000003,"currency":"USD"}},{"category":{"coding":[{"system":"https://bluebutton.cms.gov/resources/codesystem/adjudication","code":"https://bluebutton.cms.gov/resources/variables/line_prvdr_pmt_amt","display":"Line Provider Payment Amount"}]},"amount":{"value":112.41600000000001,"currency":"USD"}},{"category":{"coding":[{"system":"https://bluebutton.cms.gov/resources/codesystem/adjudication","code":"https://bluebutton.cms.gov/resources/variables/line_sbmtd_chrg_amt","display":"Line Submitted Charge Amount"}]},"amount":{"value":140.52,"currency":"USD"}},{"category":{"coding":[{"system":"https://bluebutton.cms.gov/resources/codesystem/adjudication","code":"https://bluebutton.cms.gov/resources/variables/line_alowd_chrg_amt","display":"Line Allowed Charge Amount"}]},"amount":{"value":140.52,"currency":"USD"}},{"category":{"coding":[{"system":"https://bluebutton.cms.gov/resources/codesystem/adjudication","code":"https://bluebutton.cms.gov/resources/variables/line_bene_ptb_ddctbl_amt","display":"Line Beneficiary Part B Deductible Amount"}]},"amount":{"value":0,"currency":"USD"}},{"category":{"coding":[{"system":"https://bluebutton.cms.gov/resources/codesystem/adjudication","code":"https://bluebutton.cms.gov/resources/variables/line_prcsg_ind_cd","display":"Line Processing Indicator Code"}]}}]}],"total":[{"category":{"coding":[{"system":"http://terminology.hl7.org/CodeSystem/adjudication","code":"submitted","display":"Submitted Amount"}],"text":"Submitted Amount"},"amount":{"value":129.16,"currency":"USD"}}],"payment":{"amount":{"value":112.41600000000001,"currency":"USD"}}},"request":{"method":"POST","url":"ExplanationOfBenefit"}},{"fullUrl":"Provenance/e4fa1767-5369-4e22-9ce5-9e867dd5eda9","resource":{"resourceType":"Provenance","id":"e4fa1767-5369-4e22-9ce5-9e867dd5eda9","meta":{"profile":["http://hl7.org/fhir/us/core/StructureDefinition/us-core-provenance"]},"target":[{"reference":"Patient/c68c1c0f-8fc6-42e6-a88e-a1dee7be3813"},{"reference":"Location/d8d6b15d-80b2-4fe6-8a69-ec76a4d613e2"},{"reference":"Organization/f28ce7cd-867f-3431-99e3-ab62ed072852"},{"reference":"Practitioner/a7f83620-8350-3d63-813e-627a56c3a05e"},{"reference":"PractitionerRole/641136fd-8ee2-462a-9062-bd5bfe6917e6"},{"reference":"Encounter/ed48c51b-3b76-4420-aed7-2e6c532dd668"},{"reference":"Immunization/adc21063-a0aa-4099-80a1-bfbcc40fca10"},{"reference":"DiagnosticReport/b436f367-56af-49ba-b99d-5c38491e6c0b"},{"reference":"DocumentReference/48d053b5-57aa-4166-adef-63394e8cd527"},{"reference":"Claim/f1dac895-89d8-4d40-99a7-157c17c86ecf"},{"reference":"ExplanationOfBenefit/bd461f1d-5b06-46c8-98f7-c56bab5846c3"},{"reference":"Encounter/fbede6f6-19d9-4540-8286-60ddf1a28293"},{"reference":"Immunization/587e4d6f-0dc9-446f-8b46-ac874794c824"},{"reference":"DiagnosticReport/5b4cb522-c17f-4e01-9e60-7d451b07cb20"},{"reference":"DocumentReference/d7eae182-a3bd-4a00-8816-8f9d345fd1b2"},{"reference":"Claim/1c4ae217-ba4c-45aa-807b-0a52a05f74d2"},{"reference":"ExplanationOfBenefit/a594c933-349f-4702-bca0-d34aef0186a9"}],"recorded":"2021-05-12T18:41:38.364-04:00","agent":[{"type":{"coding":[{"system":"http://terminology.hl7.org/CodeSystem/provenance-participant-type","code":"author","display":"Author"}],"text":"Author"},"who":{"reference":"Practitioner/a7f83620-8350-3d63-813e-627a56c3a05e","display":"Dr. Karlene380 Lesch175"},"onBehalfOf":{"reference":"Organization/f28ce7cd-867f-3431-99e3-ab62ed072852","display":"PCP140496"}},{"type":{"coding":[{"system":"http://hl7.org/fhir/us/core/CodeSystem/us-core-provenance-participant-type","code":"transmitter","display":"Transmitter"}],"text":"Transmitter"},"who":{"reference":"Practitioner/a7f83620-8350-3d63-813e-627a56c3a05e","display":"Dr. Karlene380 Lesch175"},"onBehalfOf":{"reference":"Organization/f28ce7cd-867f-3431-99e3-ab62ed072852","display":"PCP140496"}}]},"request":{"method":"POST","url":"Provenance"}}]}