{"resourceType":"Bundle","type":"transaction","entry":[{"fullUrl":"Patient/f305bb32-59a2-4192-a47e-552cb34c5ec9","resource":{"resourceType":"Patient","id":"f305bb32-59a2-4192-a47e-552cb34c5ec9","text":{"status":"generated","div":"<div xmlns=\"http://www.w3.org/1999/xhtml\">Generated by <a href=\"https://github.com/synthetichealth/synthea\">Synthea</a>.Version identifier: v2.4.0-876-ge3e344b2\n .   Person seed: -7379348154055058660  Population seed: 1621021121592</div>"},"extension":[{"url":"http://hl7.org/fhir/StructureDefinition/patient-mothersMaidenName","valueString":"Karlyn611 Fahey393"},{"url":"http://hl7.org/fhir/StructureDefinition/patient-birthPlace","valueAddress":{"city":"North Andover","state":"Massachusetts","country":"US"}},{"url":"http://synthetichealth.github.io/synthea/disability-adjusted-life-years","valueDecimal":0},{"url":"http://synthetichealth.github.io/synthea/quality-adjusted-life-years","valueDecimal":19}],"identifier":[{"system":"https://github.com/synthetichealth/synthea","value":"f305bb32-59a2-4192-a47e-552cb34c5ec9"},{"type":{"coding":[{"system":"http://terminology.hl7.org/CodeSystem/v2-0203","code":"MR","display":"Medical Record Number"}],"text":"Medical Record Number"},"system":"http://hospital.smarthealthit.org","value":"f305bb32-59a2-4192-a47e-552cb34c5ec9"},{"type":{"coding":[{"system":"http://terminology.hl7.org/CodeSystem/v2-0203","code":"SS","display":"Social Security Number"}],"text":"Social Security Number"},"system":"http://hl7.org/fhir/sid/us-ssn","value":"999-31-6596"},{"type":{"coding":[{"system":"http://terminology.hl7.org/CodeSystem/v2-0203","code":"DL","display":"Driver's License"}],"text":"Driver's License"},"system":"urn:oid:2.16.840.1.113883.4.3.25","value":"S99958113"},{"type":{"coding":[{"system":"http://terminology.hl7.org/CodeSystem/v2-0203","code":"PPN","display":"Passport Number"}],"text":"Passport Number"},"system":"http://standardhealthrecord.org/fhir/StructureDefinition/passportNumber","value":"X6419900X"}],"name":[{"use":"official","family":"Leuschke194","given":["Jaunita130"],"prefix":["Ms."]}],"telecom":[{"system":"phone","value":"555-205-5145","use":"home"}],"gender":"female","birthDate":"2001-03-17","address":[{"extension":[{"url":"http://hl7.org/fhir/StructureDefinition/geolocation","extension":[{"url":"latitude","valueDecimal":42.696616237331696},{"url":"longitude","valueDecimal":-71.00075556782225}]}],"line":["145 Cormier View"],"city":"Georgetown","state":"Massachusetts","country":"US"}],"maritalStatus":{"coding":[{"system":"http://terminology.hl7.org/CodeSystem/v3-MaritalStatus","code":"S","display":"Never Married"}],"text":"Never Married"},"multipleBirthBoolean":false,"communication":[{"language":{"coding":[{"system":"urn:ietf:bcp:47","code":"en-US","display":"English"}],"text":"English"}}]},"request":{"method":"POST","url":"Patient"}},{"fullUrl":"Organization/db6c9e2a-949f-3ccb-87fd-a2eeb0bdf5f1","resource":{"resourceType":"Organization","id":"db6c9e2a-949f-3ccb-87fd-a2eeb0bdf5f1","identifier":[{"system":"https://github.com/synthetichealth/synthea","value":"db6c9e2a-949f-3ccb-87fd-a2eeb0bdf5f1"}],"active":true,"type":[{"coding":[{"system":"http://terminology.hl7.org/CodeSystem/organization-type","code":"prov","display":"Healthcare Provider"}],"text":"Healthcare Provider"}],"name":"PCP40864","telecom":[{"system":"phone","value":"617-893-8807"}],"address":[{"line":["87 WASHINGTON ST"],"city":"BOXFORD","state":"MA","postalCode":"01921-1240","country":"US"}]},"request":{"method":"POST","url":"Organization"}},{"fullUrl":"Practitioner/7ea4bf1a-9ee7-3a29-8c94-b44cbf714735","resource":{"resourceType":"Practitioner","id":"7ea4bf1a-9ee7-3a29-8c94-b44cbf714735","identifier":[{"system":"http://hl7.org/fhir/sid/us-npi","value":"9999973729"}],"active":true,"name":[{"family":"Schmeler639","given":["Marx778"],"prefix":["Dr."]}],"telecom":[{"system":"email","value":"Marx778.Schmeler639@example.com","use":"work"}],"address":[{"line":["87 WASHINGTON ST"],"city":"BOXFORD","state":"MA","postalCode":"01921-1240","country":"US"}],"gender":"female"},"request":{"method":"POST","url":"Practitioner"}},{"fullUrl":"Encounter/34af22a1-3836-458c-9f1d-cb64b8c9873a","resource":{"resourceType":"Encounter","id":"34af22a1-3836-458c-9f1d-cb64b8c9873a","identifier":[{"system":"https://github.com/synthetichealth/synthea","value":"b71a4882-96de-4009-8981-631237fabb8c"}],"status":"finished","class":{"system":"http://terminology.hl7.org/CodeSystem/v3-ActCode","code":"AMB"},"type":[{"coding":[{"system":"http://snomed.info/sct","code":"162673000","display":"General examination of patient (procedure)"}],"text":"General examination of patient (procedure)"}],"subject":{"reference":"Patient/f305bb32-59a2-4192-a47e-552cb34c5ec9","display":"Ms. Jaunita130 Leuschke194"},"participant":[{"type":[{"coding":[{"system":"http://terminology.hl7.org/CodeSystem/v3-ParticipationType","code":"PPRF","display":"primary performer"}],"text":"primary performer"}],"period":{"start":"2020-05-16T03:54:57-04:00","end":"2020-05-16T04:09:57-04:00"},"individual":{"reference":"Practitioner/7ea4bf1a-9ee7-3a29-8c94-b44cbf714735","display":"Dr. Marx778 Schmeler639"}}],"period":{"start":"2020-05-16T03:54:57-04:00","end":"2020-05-16T04:09:57-04:00"},"serviceProvider":{"reference":"Organization/db6c9e2a-949f-3ccb-87fd-a2eeb0bdf5f1","display":"PCP40864"}},"request":{"method":"POST","url":"Encounter"}},{"fullUrl":"Immunization/27b0e6f1-9c37-4b0c-9243-ef1b4c91cf23","resource":{"resourceType":"Immunization","id":"27b0e6f1-9c37-4b0c-9243-ef1b4c91cf23","identifier":[{"system":"https://github.com/synthetichealth/synthea","value":"ac9a5e12-4b7b-4ba7-be55-b97c2faf27bf"}],"status":"completed","vaccineCode":{"coding":[{"system":"http://hl7.org/fhir/sid/cvx","code":"140","display":"Influenza, seasonal, injectable, preservative free"}],"text":"Influenza, seasonal, injectable, preservative free"},"patient":{"reference":"Patient/f305bb32-59a2-4192-a47e-552cb34c5ec9"},"encounter":{"reference":"Encounter/34af22a1-3836-458c-9f1d-cb64b8c9873a"},"occurrenceDateTime":"2020-05-16T03:54:57-04:00","primarySource":true},"request":{"method":"POST","url":"Immunization"}},{"fullUrl":"Claim/2886df48-15fb-404f-9d0f-d874a4422d63","resource":{"resourceType":"Claim","id":"2886df48-15fb-404f-9d0f-d874a4422d63","identifier":[{"system":"https://github.com/synthetichealth/synthea","value":"40fa980d-ad35-4885-b076-741d7a649c55"}],"status":"active","type":{"coding":[{"system":"http://terminology.hl7.org/CodeSystem/claim-type","code":"institutional"}]},"use":"claim","patient":{"reference":"Patient/f305bb32-59a2-4192-a47e-552cb34c5ec9","display":"Jaunita130 Leuschke194"},"billablePeriod":{"start":"2020-05-16T03:54:57-04:00","end":"2020-05-16T04:09:57-04:00"},"created":"2020-05-16T04:09:57-04:00","provider":{"reference":"Organization/db6c9e2a-949f-3ccb-87fd-a2eeb0bdf5f1","display":"PCP40864"},"priority":{"coding":[{"system":"http://terminology.hl7.org/CodeSystem/processpriority","code":"normal"}]},"supportingInfo":[{"sequence":1,"category":{"coding":[{"system":"http://terminology.hl7.org/CodeSystem/claiminformationcategory","code":"info"}]},"valueReference":{"reference":"Immunization/27b0e6f1-9c37-4b0c-9243-ef1b4c91cf23"}}],"insurance":[{"sequence":1,"focal":true,"coverage":{"display":"Blue Cross Blue Shield"}}],"item":[{"sequence":1,"productOrService":{"coding":[{"system":"http://snomed.info/sct","code":"162673000","display":"General examination of patient (procedure)"}],"text":"General examination of patient (procedure)"},"encounter":[{"reference":"Encounter/34af22a1-3836-458c-9f1d-cb64b8c9873a"}]},{"sequence":2,"informationSequence":[1],"productOrService":{"coding":[{"system":"http://hl7.org/fhir/sid/cvx","code":"140","display":"Influenza, seasonal, injectable, preservative free"}],"text":"Influenza, seasonal, injectable, preservative free"},"net":{"value":140.52,"currency":"USD"}}],"total":{"value":129.16,"currency":"USD"}},"request":{"method":"POST","url":"Claim"}},{"fullUrl":"ExplanationOfBenefit/ff770241-1c2c-4e4a-98b1-aa30b84b427b","resource":{"resourceType":"ExplanationOfBenefit","id":"ff770241-1c2c-4e4a-98b1-aa30b84b427b","contained":[{"resourceType":"ServiceRequest","id":"referral","status":"completed","intent":"order","subject":{"reference":"Patient/f305bb32-59a2-4192-a47e-552cb34c5ec9"},"requester":{"reference":"Practitioner/7ea4bf1a-9ee7-3a29-8c94-b44cbf714735"},"performer":[{"reference":"Practitioner/7ea4bf1a-9ee7-3a29-8c94-b44cbf714735"}]},{"resourceType":"Coverage","id":"coverage","status":"active","type":{"text":"Blue Cross Blue Shield"},"beneficiary":{"reference":"Patient/f305bb32-59a2-4192-a47e-552cb34c5ec9"},"payor":[{"display":"Blue Cross Blue Shield"}]}],"identifier":[{"system":"https://github.com/synthetichealth/synthea","value":"f4d85698-e780-4b29-80c6-fd3bcd729645"},{"system":"https://bluebutton.cms.gov/resources/variables/clm_id","value":"2886df48-15fb-404f-9d0f-d874a4422d63"},{"system":"https://bluebutton.cms.gov/resources/identifier/claim-group","value":"99999999999"}],"status":"active","type":{"coding":[{"system":"http://terminology.hl7.org/CodeSystem/claim-type","code":"institutional"}]},"use":"claim","patient":{"reference":"Patient/f305bb32-59a2-4192-a47e-552cb34c5ec9"},"billablePeriod":{"start":"2020-05-16T04:09:57-04:00","end":"2021-05-16T04:09:57-04:00"},"created":"2020-05-16T04:09:57-04:00","insurer":{"display":"Blue Cross Blue Shield"},"provider":{"reference":"Practitioner/7ea4bf1a-9ee7-3a29-8c94-b44cbf714735"},"referral":{"reference":"#referral"},"claim":{"reference":"Claim/2886df48-15fb-404f-9d0f-d874a4422d63"},"outcome":"complete","careTeam":[{"sequence":1,"provider":{"reference":"Practitioner/7ea4bf1a-9ee7-3a29-8c94-b44cbf714735"},"role":{"coding":[{"system":"http://terminology.hl7.org/CodeSystem/claimcareteamrole","code":"primary","display":"Primary Care Practitioner"}]}}],"insurance":[{"focal":true,"coverage":{"reference":"#coverage","display":"Blue Cross Blue Shield"}}],"item":[{"sequence":1,"category":{"coding":[{"system":"https://bluebutton.cms.gov/resources/variables/line_cms_type_srvc_cd","code":"1","display":"Medical care"}]},"productOrService":{"coding":[{"system":"http://snomed.info/sct","code":"162673000","display":"General examination of patient (procedure)"}],"text":"General examination of patient (procedure)"},"servicedPeriod":{"start":"2020-05-16T03:54:57-04:00","end":"2020-05-16T04:09:57-04:00"},"locationCodeableConcept":{"coding":[{"system":"http://terminology.hl7.org/CodeSystem/ex-serviceplace","code":"19","display":"Off Campus-Outpatient Hospital"}]},"encounter":[{"reference":"Encounter/34af22a1-3836-458c-9f1d-cb64b8c9873a"}]},{"sequence":2,"informationSequence":[1],"category":{"coding":[{"system":"https://bluebutton.cms.gov/resources/variables/line_cms_type_srvc_cd","code":"1","display":"Medical care"}]},"productOrService":{"coding":[{"system":"http://hl7.org/fhir/sid/cvx","code":"140","display":"Influenza, seasonal, injectable, preservative free"}],"text":"Influenza, seasonal, injectable, preservative free"},"servicedPeriod":{"start":"2020-05-16T03:54:57-04:00","end":"2020-05-16T04:09:57-04:00"},"locationCodeableConcept":{"coding":[{"system":"http://terminology.hl7.org/CodeSystem/ex-serviceplace","code":"19","display":"Off Campus-Outpatient Hospital"}]},"net":{"value":140.52,"currency":"USD"},"adjudication":[{"category":{"coding":[{"system":"https://bluebutton.cms.gov/resources/codesystem/adjudication","code":"https://bluebutton.cms.gov/resources/variables/line_coinsrnc_amt","display":"Line Beneficiary Coinsurance Amount"}]},"amount":{"value":28.104000000000003,"currency":"USD"}},{"category":{"coding":[{"system":"https://bluebutton.cms.gov/resources/codesystem/adjudication","code":"https://bluebutton.cms.gov/resources/variables/line_prvdr_pmt_amt","display":"Line Provider Payment Amount"}]},"amount":{"value":112.41600000000001,"currency":"USD"}},{"category":{"coding":[{"system":"https://bluebutton.cms.gov/resources/codesystem/adjudication","code":"https://bluebutton.cms.gov/resources/variables/line_sbmtd_chrg_amt","display":"Line Submitted Charge Amount"}]},"amount":{"value":140.52,"currency":"USD"}},{"category":{"coding":[{"system":"https://bluebutton.cms.gov/resources/codesystem/adjudication","code":"https://bluebutton.cms.gov/resources/variables/line_alowd_chrg_amt","display":"Line Allowed Charge Amount"}]},"amount":{"value":140.52,"currency":"USD"}},{"category":{"coding":[{"system":"https://bluebutton.cms.gov/resources/codesystem/adjudication","code":"https://bluebutton.cms.gov/resources/variables/line_bene_ptb_ddctbl_amt","display":"Line Beneficiary Part B Deductible Amount"}]},"amount":{"value":0,"currency":"USD"}},{"category":{"coding":[{"system":"https://bluebutton.cms.gov/resources/codesystem/adjudication","code":"https://bluebutton.cms.gov/resources/variables/line_prcsg_ind_cd","display":"Line Processing Indicator Code"}]}}]}],"total":[{"category":{"coding":[{"system":"http://terminology.hl7.org/CodeSystem/adjudication","code":"submitted","display":"Submitted Amount"}],"text":"Submitted Amount"},"amount":{"value":129.16,"currency":"USD"}}],"payment":{"amount":{"value":112.41600000000001,"currency":"USD"}}},"request":{"method":"POST","url":"ExplanationOfBenefit"}}]}