{"resourceType":"Bundle","type":"transaction","entry":[{"fullUrl":"Patient/503d2fd5-b644-4d07-92a4-5f0d01e45cc8","resource":{"resourceType":"Patient","id":"503d2fd5-b644-4d07-92a4-5f0d01e45cc8","meta":{"profile":["http://hl7.org/fhir/us/core/StructureDefinition/us-core-patient"]},"text":{"status":"generated","div":"<div xmlns=\"http://www.w3.org/1999/xhtml\">Generated by <a href=\"https://github.com/synthetichealth/synthea\">Synthea</a>.Version identifier: v2.4.0-876-ge3e344b2\n .   Person seed: 4857540002550803001  Population seed: 1620845753740</div>"},"extension":[{"url":"http://hl7.org/fhir/us/core/StructureDefinition/us-core-race","extension":[{"url":"ombCategory","valueCoding":{"system":"urn:oid:2.16.840.1.113883.6.238","code":"2106-3","display":"White"}},{"url":"text","valueString":"White"}]},{"url":"http://hl7.org/fhir/us/core/StructureDefinition/us-core-ethnicity","extension":[{"url":"ombCategory","valueCoding":{"system":"urn:oid:2.16.840.1.113883.6.238","code":"2186-5","display":"Not Hispanic or Latino"}},{"url":"text","valueString":"Not Hispanic or Latino"}]},{"url":"http://hl7.org/fhir/StructureDefinition/patient-mothersMaidenName","valueString":"Sunshine777 Greenholt190"},{"url":"http://hl7.org/fhir/us/core/StructureDefinition/us-core-birthsex","valueCode":"M"},{"url":"http://hl7.org/fhir/StructureDefinition/patient-birthPlace","valueAddress":{"city":"Winchester","state":"Massachusetts","country":"US"}},{"url":"http://synthetichealth.github.io/synthea/disability-adjusted-life-years","valueDecimal":0},{"url":"http://synthetichealth.github.io/synthea/quality-adjusted-life-years","valueDecimal":19}],"identifier":[{"system":"https://github.com/synthetichealth/synthea","value":"503d2fd5-b644-4d07-92a4-5f0d01e45cc8"},{"type":{"coding":[{"system":"http://terminology.hl7.org/CodeSystem/v2-0203","code":"MR","display":"Medical Record Number"}],"text":"Medical Record Number"},"system":"http://hospital.smarthealthit.org","value":"503d2fd5-b644-4d07-92a4-5f0d01e45cc8"},{"type":{"coding":[{"system":"http://terminology.hl7.org/CodeSystem/v2-0203","code":"SS","display":"Social Security Number"}],"text":"Social Security Number"},"system":"http://hl7.org/fhir/sid/us-ssn","value":"999-52-5211"},{"type":{"coding":[{"system":"http://terminology.hl7.org/CodeSystem/v2-0203","code":"DL","display":"Driver's License"}],"text":"Driver's License"},"system":"urn:oid:2.16.840.1.113883.4.3.25","value":"S99938669"}],"name":[{"use":"official","family":"Bernhard322","given":["Roy364"],"prefix":["Mr."]}],"telecom":[{"system":"phone","value":"555-767-9689","use":"home"}],"gender":"male","birthDate":"2001-09-30","address":[{"extension":[{"url":"http://hl7.org/fhir/StructureDefinition/geolocation","extension":[{"url":"latitude","valueDecimal":42.18067107757431},{"url":"longitude","valueDecimal":-71.67399196891648}]}],"line":["652 McDermott Bypass"],"city":"Grafton","state":"MA","country":"US"}],"maritalStatus":{"coding":[{"system":"http://terminology.hl7.org/CodeSystem/v3-MaritalStatus","code":"S","display":"Never Married"}],"text":"Never Married"},"multipleBirthBoolean":false,"communication":[{"language":{"coding":[{"system":"urn:ietf:bcp:47","code":"en-US","display":"English"}],"text":"English"}}]},"request":{"method":"POST","url":"Patient"}},{"fullUrl":"Location/463fc781-da4d-4a0b-b676-4e19ef375ae7","resource":{"resourceType":"Location","id":"463fc781-da4d-4a0b-b676-4e19ef375ae7","meta":{"profile":["http://hl7.org/fhir/us/core/StructureDefinition/us-core-location"]},"identifier":[{"system":"https://github.com/synthetichealth/synthea","value":"b6613ec7-1973-40a7-893c-22a55f8e87fb"}],"status":"active","name":"PCP9022","telecom":[{"system":"phone","value":"508-839-3616"}],"address":{"line":["1 HOLLYWOOD DR"],"city":"GRAFTON","state":"MA","postalCode":"01536-1614","country":"US"},"position":{"longitude":-71.683644,"latitude":42.209151},"managingOrganization":{"reference":"Organization/32836213-4ac7-3021-aad8-6383f3ced351","display":"PCP9022"}},"request":{"method":"POST","url":"Location"}},{"fullUrl":"Organization/32836213-4ac7-3021-aad8-6383f3ced351","resource":{"resourceType":"Organization","id":"32836213-4ac7-3021-aad8-6383f3ced351","meta":{"profile":["http://hl7.org/fhir/us/core/StructureDefinition/us-core-organization"]},"identifier":[{"system":"https://github.com/synthetichealth/synthea","value":"32836213-4ac7-3021-aad8-6383f3ced351"}],"active":true,"type":[{"coding":[{"system":"http://terminology.hl7.org/CodeSystem/organization-type","code":"prov","display":"Healthcare Provider"}],"text":"Healthcare Provider"}],"name":"PCP9022","telecom":[{"system":"phone","value":"508-839-3616"}],"address":[{"line":["1 HOLLYWOOD DR"],"city":"GRAFTON","state":"MA","postalCode":"01536-1614","country":"US"}]},"request":{"method":"POST","url":"Organization"}},{"fullUrl":"Practitioner/90c6c89d-c6b9-306d-b1ba-91dbf105a7ac","resource":{"resourceType":"Practitioner","id":"90c6c89d-c6b9-306d-b1ba-91dbf105a7ac","meta":{"profile":["http://hl7.org/fhir/us/core/StructureDefinition/us-core-practitioner"]},"identifier":[{"system":"http://hl7.org/fhir/sid/us-npi","value":"9999993609"}],"active":true,"name":[{"family":"Deckow585","given":["Bobby524"],"prefix":["Dr."]}],"telecom":[{"extension":[{"url":"http://hl7.org/fhir/us/core/StructureDefinition/us-core-direct","valueBoolean":true}],"system":"email","value":"Bobby524.Deckow585@example.com","use":"work"}],"address":[{"line":["1 HOLLYWOOD DR"],"city":"GRAFTON","state":"MA","postalCode":"01536-1614","country":"US"}],"gender":"female"},"request":{"method":"POST","url":"Practitioner"}},{"fullUrl":"PractitionerRole/e409617c-e023-44db-aa92-dc6824b5e30b","resource":{"resourceType":"PractitionerRole","id":"e409617c-e023-44db-aa92-dc6824b5e30b","meta":{"profile":["http://hl7.org/fhir/us/core/StructureDefinition/us-core-practitionerrole"]},"practitioner":{"reference":"Practitioner/90c6c89d-c6b9-306d-b1ba-91dbf105a7ac","display":"Dr. Bobby524 Deckow585"},"organization":{"reference":"Organization/32836213-4ac7-3021-aad8-6383f3ced351","display":"PCP9022"},"code":[{"coding":[{"system":"http://nucc.org/provider-taxonomy","code":"208D00000X","display":"General Practice"}],"text":"General Practice"}],"specialty":[{"coding":[{"system":"http://nucc.org/provider-taxonomy","code":"208D00000X","display":"General Practice"}],"text":"General Practice"}],"location":[{"reference":"Location/463fc781-da4d-4a0b-b676-4e19ef375ae7","display":"PCP9022"}],"telecom":[{"system":"phone","value":"508-839-3616"},{"extension":[{"url":"http://hl7.org/fhir/us/core/StructureDefinition/us-core-direct","valueBoolean":true}],"system":"email","value":"Bobby524.Deckow585@example.com","use":"work"}]},"request":{"method":"POST","url":"PractitionerRole"}},{"fullUrl":"Encounter/980912e0-553f-424c-8bb3-f942c8e5fb82","resource":{"resourceType":"Encounter","id":"980912e0-553f-424c-8bb3-f942c8e5fb82","meta":{"profile":["http://hl7.org/fhir/us/core/StructureDefinition/us-core-encounter"]},"identifier":[{"system":"https://github.com/synthetichealth/synthea","value":"5cfff0c5-74cc-421a-8a90-728050d3a7f9"},{"use":"official","system":"https://github.com/synthetichealth/synthea","value":"980912e0-553f-424c-8bb3-f942c8e5fb82"}],"status":"finished","class":{"system":"http://terminology.hl7.org/CodeSystem/v3-ActCode","code":"AMB"},"type":[{"coding":[{"system":"http://snomed.info/sct","code":"162673000","display":"General examination of patient (procedure)"}],"text":"General examination of patient (procedure)"}],"subject":{"reference":"Patient/503d2fd5-b644-4d07-92a4-5f0d01e45cc8","display":"Mr. Roy364 Bernhard322"},"participant":[{"type":[{"coding":[{"system":"http://terminology.hl7.org/CodeSystem/v3-ParticipationType","code":"PPRF","display":"primary performer"}],"text":"primary performer"}],"period":{"start":"2019-11-24T03:16:17-05:00","end":"2019-11-24T03:31:17-05:00"},"individual":{"reference":"Practitioner/90c6c89d-c6b9-306d-b1ba-91dbf105a7ac","display":"Dr. Bobby524 Deckow585"}}],"period":{"start":"2019-11-24T03:16:17-05:00","end":"2019-11-24T03:31:17-05:00"},"location":[{"location":{"reference":"Location/463fc781-da4d-4a0b-b676-4e19ef375ae7","display":"PCP9022"}}],"serviceProvider":{"reference":"Organization/32836213-4ac7-3021-aad8-6383f3ced351","display":"PCP9022"}},"request":{"method":"POST","url":"Encounter"}},{"fullUrl":"Immunization/9bcf53ca-dae5-4baa-92d5-4fb4bd2a344c","resource":{"resourceType":"Immunization","id":"9bcf53ca-dae5-4baa-92d5-4fb4bd2a344c","meta":{"profile":["http://hl7.org/fhir/us/core/StructureDefinition/us-core-immunization"]},"identifier":[{"system":"https://github.com/synthetichealth/synthea","value":"f4140a4c-5ed7-42df-b013-c44f8c78dc9c"}],"status":"completed","vaccineCode":{"coding":[{"system":"http://hl7.org/fhir/sid/cvx","code":"140","display":"Influenza, seasonal, injectable, preservative free"}],"text":"Influenza, seasonal, injectable, preservative free"},"patient":{"reference":"Patient/503d2fd5-b644-4d07-92a4-5f0d01e45cc8"},"encounter":{"reference":"Encounter/980912e0-553f-424c-8bb3-f942c8e5fb82"},"occurrenceDateTime":"2019-11-24T03:16:17-05:00","primarySource":true,"location":{"reference":"Location/463fc781-da4d-4a0b-b676-4e19ef375ae7","display":"PCP9022"}},"request":{"method":"POST","url":"Immunization"}},{"fullUrl":"DiagnosticReport/acedfc92-e5fd-493e-be55-8d654ebd5958","resource":{"resourceType":"DiagnosticReport","id":"acedfc92-e5fd-493e-be55-8d654ebd5958","meta":{"profile":["http://hl7.org/fhir/us/core/StructureDefinition/us-core-diagnosticreport-note"]},"identifier":[{"system":"https://github.com/synthetichealth/synthea","value":"290ea486-f678-447b-aa2d-906e37742eb2"}],"status":"final","category":[{"coding":[{"system":"http://loinc.org","code":"34117-2","display":"History and physical note"},{"system":"http://loinc.org","code":"51847-2","display":"Evaluation+Plan note"}]}],"code":{"coding":[{"system":"http://loinc.org","code":"34117-2","display":"History and physical note"},{"system":"http://loinc.org","code":"51847-2","display":"Evaluation+Plan note"}]},"subject":{"reference":"Patient/503d2fd5-b644-4d07-92a4-5f0d01e45cc8"},"encounter":{"reference":"Encounter/980912e0-553f-424c-8bb3-f942c8e5fb82"},"effectiveDateTime":"2019-11-24T03:16:17-05:00","issued":"2019-11-24T03:16:17.629-05:00","performer":[{"reference":"Practitioner/90c6c89d-c6b9-306d-b1ba-91dbf105a7ac","display":"Dr. Bobby524 Deckow585"}],"presentedForm":[{"contentType":"text/plain","data":"CjIwMTktMTEtMjQKCiMgQ2hpZWYgQ29tcGxhaW50Ck5vIGNvbXBsYWludHMuCgojIEhpc3Rvcnkgb2YgUHJlc2VudCBJbGxuZXNzClJveTM2NCBpcyBhIDE4IHllYXItb2xkIG5vbi1oaXNwYW5pYyB3aGl0ZSBtYWxlLgoKIyBTb2NpYWwgSGlzdG9yeQogUGF0aWVudCBpcyBhbiBhY3RpdmUgc21va2VyLiBQYXRpZW50IGlkZW50aWZpZXMgYXMgaGV0ZXJvc2V4dWFsLgoKUGF0aWVudCBjb21lcyBmcm9tIGEgaGlnaCBzb2Npb2Vjb25vbWljIGJhY2tncm91bmQuIFBhdGllbnQgaXMgYSBjb2xsZWdlIGdyYWR1YXRlLiBQYXRpZW50IGN1cnJlbnRseSBoYXMgQmx1ZSBDcm9zcyBCbHVlIFNoaWVsZC4KCiMgQWxsZXJnaWVzCk5vIEtub3duIEFsbGVyZ2llcy4KCiMgTWVkaWNhdGlvbnMKTm8gQWN0aXZlIE1lZGljYXRpb25zLgoKIyBBc3Nlc3NtZW50IGFuZCBQbGFuCgoKIyMgUGxhbgpQYXRpZW50IHdhcyBnaXZlbiB0aGUgZm9sbG93aW5nIGltbXVuaXphdGlvbnM6IGluZmx1ZW56YSwgc2Vhc29uYWwsIGluamVjdGFibGUsIHByZXNlcnZhdGl2ZSBmcmVlLiAK"}]},"request":{"method":"POST","url":"DiagnosticReport"}},{"fullUrl":"DocumentReference/7f8bebf4-c115-4185-be17-c1bcd6a4bbcb","resource":{"resourceType":"DocumentReference","id":"7f8bebf4-c115-4185-be17-c1bcd6a4bbcb","meta":{"profile":["http://hl7.org/fhir/us/core/StructureDefinition/us-core-documentreference"]},"identifier":[{"system":"urn:ietf:rfc:3986","value":"acedfc92-e5fd-493e-be55-8d654ebd5958"}],"status":"superseded","type":{"coding":[{"system":"http://loinc.org","code":"34117-2","display":"History and physical note"},{"system":"http://loinc.org","code":"51847-2","display":"Evaluation+Plan note"}]},"category":[{"coding":[{"system":"http://hl7.org/fhir/us/core/CodeSystem/us-core-documentreference-category","code":"clinical-note","display":"Clinical Note"}]}],"subject":{"reference":"Patient/503d2fd5-b644-4d07-92a4-5f0d01e45cc8"},"date":"2019-11-24T03:16:17.629-05:00","author":[{"reference":"Practitioner/90c6c89d-c6b9-306d-b1ba-91dbf105a7ac","display":"Dr. Bobby524 Deckow585"}],"custodian":{"reference":"Organization/32836213-4ac7-3021-aad8-6383f3ced351","display":"PCP9022"},"content":[{"attachment":{"contentType":"text/plain","data":"CjIwMTktMTEtMjQKCiMgQ2hpZWYgQ29tcGxhaW50Ck5vIGNvbXBsYWludHMuCgojIEhpc3Rvcnkgb2YgUHJlc2VudCBJbGxuZXNzClJveTM2NCBpcyBhIDE4IHllYXItb2xkIG5vbi1oaXNwYW5pYyB3aGl0ZSBtYWxlLgoKIyBTb2NpYWwgSGlzdG9yeQogUGF0aWVudCBpcyBhbiBhY3RpdmUgc21va2VyLiBQYXRpZW50IGlkZW50aWZpZXMgYXMgaGV0ZXJvc2V4dWFsLgoKUGF0aWVudCBjb21lcyBmcm9tIGEgaGlnaCBzb2Npb2Vjb25vbWljIGJhY2tncm91bmQuIFBhdGllbnQgaXMgYSBjb2xsZWdlIGdyYWR1YXRlLiBQYXRpZW50IGN1cnJlbnRseSBoYXMgQmx1ZSBDcm9zcyBCbHVlIFNoaWVsZC4KCiMgQWxsZXJnaWVzCk5vIEtub3duIEFsbGVyZ2llcy4KCiMgTWVkaWNhdGlvbnMKTm8gQWN0aXZlIE1lZGljYXRpb25zLgoKIyBBc3Nlc3NtZW50IGFuZCBQbGFuCgoKIyMgUGxhbgpQYXRpZW50IHdhcyBnaXZlbiB0aGUgZm9sbG93aW5nIGltbXVuaXphdGlvbnM6IGluZmx1ZW56YSwgc2Vhc29uYWwsIGluamVjdGFibGUsIHByZXNlcnZhdGl2ZSBmcmVlLiAK"},"format":{"system":"http://ihe.net/fhir/ValueSet/IHE.FormatCode.codesystem","code":"urn:ihe:iti:xds:2017:mimeTypeSufficient","display":"mimeType Sufficient"}}],"context":{"encounter":[{"reference":"Encounter/980912e0-553f-424c-8bb3-f942c8e5fb82"}],"period":{"start":"2019-11-24T03:16:17-05:00","end":"2019-11-24T03:31:17-05:00"}}},"request":{"method":"POST","url":"DocumentReference"}},{"fullUrl":"Claim/f3ee7f27-3df1-43cb-af1a-7f16a6f3a90b","resource":{"resourceType":"Claim","id":"f3ee7f27-3df1-43cb-af1a-7f16a6f3a90b","identifier":[{"system":"https://github.com/synthetichealth/synthea","value":"0a3eaf34-0214-42df-8d95-72860bbce4bb"}],"status":"active","type":{"coding":[{"system":"http://terminology.hl7.org/CodeSystem/claim-type","code":"institutional"}]},"use":"claim","patient":{"reference":"Patient/503d2fd5-b644-4d07-92a4-5f0d01e45cc8","display":"Roy364 Bernhard322"},"billablePeriod":{"start":"2019-11-24T03:16:17-05:00","end":"2019-11-24T03:31:17-05:00"},"created":"2019-11-24T03:31:17-05:00","provider":{"reference":"Organization/32836213-4ac7-3021-aad8-6383f3ced351","display":"PCP9022"},"priority":{"coding":[{"system":"http://terminology.hl7.org/CodeSystem/processpriority","code":"normal"}]},"facility":{"reference":"Location/463fc781-da4d-4a0b-b676-4e19ef375ae7","display":"PCP9022"},"supportingInfo":[{"sequence":1,"category":{"coding":[{"system":"http://terminology.hl7.org/CodeSystem/claiminformationcategory","code":"info"}]},"valueReference":{"reference":"Immunization/9bcf53ca-dae5-4baa-92d5-4fb4bd2a344c"}}],"insurance":[{"sequence":1,"focal":true,"coverage":{"display":"Blue Cross Blue Shield"}}],"item":[{"sequence":1,"productOrService":{"coding":[{"system":"http://snomed.info/sct","code":"162673000","display":"General examination of patient (procedure)"}],"text":"General examination of patient (procedure)"},"encounter":[{"reference":"Encounter/980912e0-553f-424c-8bb3-f942c8e5fb82"}]},{"sequence":2,"informationSequence":[1],"productOrService":{"coding":[{"system":"http://hl7.org/fhir/sid/cvx","code":"140","display":"Influenza, seasonal, injectable, preservative free"}],"text":"Influenza, seasonal, injectable, preservative free"},"net":{"value":140.52,"currency":"USD"}}],"total":{"value":129.16,"currency":"USD"}},"request":{"method":"POST","url":"Claim"}},{"fullUrl":"ExplanationOfBenefit/87530883-d30a-4238-ac37-e2f168df78e9","resource":{"resourceType":"ExplanationOfBenefit","id":"87530883-d30a-4238-ac37-e2f168df78e9","contained":[{"resourceType":"ServiceRequest","id":"referral","status":"completed","intent":"order","subject":{"reference":"Patient/503d2fd5-b644-4d07-92a4-5f0d01e45cc8"},"requester":{"reference":"Practitioner/90c6c89d-c6b9-306d-b1ba-91dbf105a7ac"},"performer":[{"reference":"Practitioner/90c6c89d-c6b9-306d-b1ba-91dbf105a7ac"}]},{"resourceType":"Coverage","id":"coverage","status":"active","type":{"text":"Blue Cross Blue Shield"},"beneficiary":{"reference":"Patient/503d2fd5-b644-4d07-92a4-5f0d01e45cc8"},"payor":[{"display":"Blue Cross Blue Shield"}]}],"identifier":[{"system":"https://github.com/synthetichealth/synthea","value":"ec31a9ab-fb29-4b03-ac90-5eefd7c62c06"},{"system":"https://bluebutton.cms.gov/resources/variables/clm_id","value":"f3ee7f27-3df1-43cb-af1a-7f16a6f3a90b"},{"system":"https://bluebutton.cms.gov/resources/identifier/claim-group","value":"99999999999"}],"status":"active","type":{"coding":[{"system":"http://terminology.hl7.org/CodeSystem/claim-type","code":"institutional"}]},"use":"claim","patient":{"reference":"Patient/503d2fd5-b644-4d07-92a4-5f0d01e45cc8"},"billablePeriod":{"start":"2019-11-24T03:31:17-05:00","end":"2020-11-24T03:31:17-05:00"},"created":"2019-11-24T03:31:17-05:00","insurer":{"display":"Blue Cross Blue Shield"},"provider":{"reference":"Practitioner/90c6c89d-c6b9-306d-b1ba-91dbf105a7ac"},"referral":{"reference":"#referral"},"facility":{"reference":"Location/463fc781-da4d-4a0b-b676-4e19ef375ae7","display":"PCP9022"},"claim":{"reference":"Claim/f3ee7f27-3df1-43cb-af1a-7f16a6f3a90b"},"outcome":"complete","careTeam":[{"sequence":1,"provider":{"reference":"Practitioner/90c6c89d-c6b9-306d-b1ba-91dbf105a7ac"},"role":{"coding":[{"system":"http://terminology.hl7.org/CodeSystem/claimcareteamrole","code":"primary","display":"Primary Care Practitioner"}]}}],"insurance":[{"focal":true,"coverage":{"reference":"#coverage","display":"Blue Cross Blue Shield"}}],"item":[{"sequence":1,"category":{"coding":[{"system":"https://bluebutton.cms.gov/resources/variables/line_cms_type_srvc_cd","code":"1","display":"Medical care"}]},"productOrService":{"coding":[{"system":"http://snomed.info/sct","code":"162673000","display":"General examination of patient (procedure)"}],"text":"General examination of patient (procedure)"},"servicedPeriod":{"start":"2019-11-24T03:16:17-05:00","end":"2019-11-24T03:31:17-05:00"},"locationCodeableConcept":{"coding":[{"system":"http://terminology.hl7.org/CodeSystem/ex-serviceplace","code":"19","display":"Off Campus-Outpatient Hospital"}]},"encounter":[{"reference":"Encounter/980912e0-553f-424c-8bb3-f942c8e5fb82"}]},{"sequence":2,"informationSequence":[1],"category":{"coding":[{"system":"https://bluebutton.cms.gov/resources/variables/line_cms_type_srvc_cd","code":"1","display":"Medical care"}]},"productOrService":{"coding":[{"system":"http://hl7.org/fhir/sid/cvx","code":"140","display":"Influenza, seasonal, injectable, preservative free"}],"text":"Influenza, seasonal, injectable, preservative free"},"servicedPeriod":{"start":"2019-11-24T03:16:17-05:00","end":"2019-11-24T03:31:17-05:00"},"locationCodeableConcept":{"coding":[{"system":"http://terminology.hl7.org/CodeSystem/ex-serviceplace","code":"19","display":"Off Campus-Outpatient Hospital"}]},"net":{"value":140.52,"currency":"USD"},"adjudication":[{"category":{"coding":[{"system":"https://bluebutton.cms.gov/resources/codesystem/adjudication","code":"https://bluebutton.cms.gov/resources/variables/line_coinsrnc_amt","display":"Line Beneficiary Coinsurance Amount"}]},"amount":{"value":28.104000000000003,"currency":"USD"}},{"category":{"coding":[{"system":"https://bluebutton.cms.gov/resources/codesystem/adjudication","code":"https://bluebutton.cms.gov/resources/variables/line_prvdr_pmt_amt","display":"Line Provider Payment Amount"}]},"amount":{"value":112.41600000000001,"currency":"USD"}},{"category":{"coding":[{"system":"https://bluebutton.cms.gov/resources/codesystem/adjudication","code":"https://bluebutton.cms.gov/resources/variables/line_sbmtd_chrg_amt","display":"Line Submitted Charge Amount"}]},"amount":{"value":140.52,"currency":"USD"}},{"category":{"coding":[{"system":"https://bluebutton.cms.gov/resources/codesystem/adjudication","code":"https://bluebutton.cms.gov/resources/variables/line_alowd_chrg_amt","display":"Line Allowed Charge Amount"}]},"amount":{"value":140.52,"currency":"USD"}},{"category":{"coding":[{"system":"https://bluebutton.cms.gov/resources/codesystem/adjudication","code":"https://bluebutton.cms.gov/resources/variables/line_bene_ptb_ddctbl_amt","display":"Line Beneficiary Part B Deductible Amount"}]},"amount":{"value":0,"currency":"USD"}},{"category":{"coding":[{"system":"https://bluebutton.cms.gov/resources/codesystem/adjudication","code":"https://bluebutton.cms.gov/resources/variables/line_prcsg_ind_cd","display":"Line Processing Indicator Code"}]}}]}],"total":[{"category":{"coding":[{"system":"http://terminology.hl7.org/CodeSystem/adjudication","code":"submitted","display":"Submitted Amount"}],"text":"Submitted Amount"},"amount":{"value":129.16,"currency":"USD"}}],"payment":{"amount":{"value":112.41600000000001,"currency":"USD"}}},"request":{"method":"POST","url":"ExplanationOfBenefit"}},{"fullUrl":"Encounter/3a7643c0-8c94-410a-b1d1-558ca71d9241","resource":{"resourceType":"Encounter","id":"3a7643c0-8c94-410a-b1d1-558ca71d9241","meta":{"profile":["http://hl7.org/fhir/us/core/StructureDefinition/us-core-encounter"]},"identifier":[{"system":"https://github.com/synthetichealth/synthea","value":"a41766e9-234c-4047-9196-bb8acce33e64"},{"use":"official","system":"https://github.com/synthetichealth/synthea","value":"3a7643c0-8c94-410a-b1d1-558ca71d9241"}],"status":"finished","class":{"system":"http://terminology.hl7.org/CodeSystem/v3-ActCode","code":"AMB"},"type":[{"coding":[{"system":"http://snomed.info/sct","code":"162673000","display":"General examination of patient (procedure)"}],"text":"General examination of patient (procedure)"}],"subject":{"reference":"Patient/503d2fd5-b644-4d07-92a4-5f0d01e45cc8","display":"Mr. Roy364 Bernhard322"},"participant":[{"type":[{"coding":[{"system":"http://terminology.hl7.org/CodeSystem/v3-ParticipationType","code":"PPRF","display":"primary performer"}],"text":"primary performer"}],"period":{"start":"2020-11-29T03:16:17-05:00","end":"2020-11-29T03:31:17-05:00"},"individual":{"reference":"Practitioner/90c6c89d-c6b9-306d-b1ba-91dbf105a7ac","display":"Dr. Bobby524 Deckow585"}}],"period":{"start":"2020-11-29T03:16:17-05:00","end":"2020-11-29T03:31:17-05:00"},"location":[{"location":{"reference":"Location/463fc781-da4d-4a0b-b676-4e19ef375ae7","display":"PCP9022"}}],"serviceProvider":{"reference":"Organization/32836213-4ac7-3021-aad8-6383f3ced351","display":"PCP9022"}},"request":{"method":"POST","url":"Encounter"}},{"fullUrl":"Immunization/a824419d-8ffc-4776-817d-7e7c9d303b25","resource":{"resourceType":"Immunization","id":"a824419d-8ffc-4776-817d-7e7c9d303b25","meta":{"profile":["http://hl7.org/fhir/us/core/StructureDefinition/us-core-immunization"]},"identifier":[{"system":"https://github.com/synthetichealth/synthea","value":"1a2813c3-3a9a-4ea0-8d4b-cb02b0e5723c"}],"status":"completed","vaccineCode":{"coding":[{"system":"http://hl7.org/fhir/sid/cvx","code":"140","display":"Influenza, seasonal, injectable, preservative free"}],"text":"Influenza, seasonal, injectable, preservative free"},"patient":{"reference":"Patient/503d2fd5-b644-4d07-92a4-5f0d01e45cc8"},"encounter":{"reference":"Encounter/3a7643c0-8c94-410a-b1d1-558ca71d9241"},"occurrenceDateTime":"2020-11-29T03:16:17-05:00","primarySource":true,"location":{"reference":"Location/463fc781-da4d-4a0b-b676-4e19ef375ae7","display":"PCP9022"}},"request":{"method":"POST","url":"Immunization"}},{"fullUrl":"DiagnosticReport/08f07e04-ad66-4d78-894a-8e8f5235b9f5","resource":{"resourceType":"DiagnosticReport","id":"08f07e04-ad66-4d78-894a-8e8f5235b9f5","meta":{"profile":["http://hl7.org/fhir/us/core/StructureDefinition/us-core-diagnosticreport-note"]},"identifier":[{"system":"https://github.com/synthetichealth/synthea","value":"3e4526d1-6068-42da-9466-e8b0af15fa9f"}],"status":"final","category":[{"coding":[{"system":"http://loinc.org","code":"34117-2","display":"History and physical note"},{"system":"http://loinc.org","code":"51847-2","display":"Evaluation+Plan note"}]}],"code":{"coding":[{"system":"http://loinc.org","code":"34117-2","display":"History and physical note"},{"system":"http://loinc.org","code":"51847-2","display":"Evaluation+Plan note"}]},"subject":{"reference":"Patient/503d2fd5-b644-4d07-92a4-5f0d01e45cc8"},"encounter":{"reference":"Encounter/3a7643c0-8c94-410a-b1d1-558ca71d9241"},"effectiveDateTime":"2020-11-29T03:16:17-05:00","issued":"2020-11-29T03:16:17.629-05:00","performer":[{"reference":"Practitioner/90c6c89d-c6b9-306d-b1ba-91dbf105a7ac","display":"Dr. Bobby524 Deckow585"}],"presentedForm":[{"contentType":"text/plain","data":"CjIwMjAtMTEtMjkKCiMgQ2hpZWYgQ29tcGxhaW50Ck5vIGNvbXBsYWludHMuCgojIEhpc3Rvcnkgb2YgUHJlc2VudCBJbGxuZXNzClJveTM2NCBpcyBhIDE5IHllYXItb2xkIG5vbi1oaXNwYW5pYyB3aGl0ZSBtYWxlLgoKIyBTb2NpYWwgSGlzdG9yeQogUGF0aWVudCBpcyBhbiBhY3RpdmUgc21va2VyLiBQYXRpZW50IGlkZW50aWZpZXMgYXMgaGV0ZXJvc2V4dWFsLgoKUGF0aWVudCBjb21lcyBmcm9tIGEgaGlnaCBzb2Npb2Vjb25vbWljIGJhY2tncm91bmQuIFBhdGllbnQgaXMgYSBjb2xsZWdlIGdyYWR1YXRlLiBQYXRpZW50IGN1cnJlbnRseSBoYXMgQmx1ZSBDcm9zcyBCbHVlIFNoaWVsZC4KCiMgQWxsZXJnaWVzCk5vIEtub3duIEFsbGVyZ2llcy4KCiMgTWVkaWNhdGlvbnMKTm8gQWN0aXZlIE1lZGljYXRpb25zLgoKIyBBc3Nlc3NtZW50IGFuZCBQbGFuCgoKIyMgUGxhbgpQYXRpZW50IHdhcyBnaXZlbiB0aGUgZm9sbG93aW5nIGltbXVuaXphdGlvbnM6IGluZmx1ZW56YSwgc2Vhc29uYWwsIGluamVjdGFibGUsIHByZXNlcnZhdGl2ZSBmcmVlLiAK"}]},"request":{"method":"POST","url":"DiagnosticReport"}},{"fullUrl":"DocumentReference/0523af58-e929-45d9-9fdf-adb72e5c780f","resource":{"resourceType":"DocumentReference","id":"0523af58-e929-45d9-9fdf-adb72e5c780f","meta":{"profile":["http://hl7.org/fhir/us/core/StructureDefinition/us-core-documentreference"]},"identifier":[{"system":"urn:ietf:rfc:3986","value":"08f07e04-ad66-4d78-894a-8e8f5235b9f5"}],"status":"current","type":{"coding":[{"system":"http://loinc.org","code":"34117-2","display":"History and physical note"},{"system":"http://loinc.org","code":"51847-2","display":"Evaluation+Plan note"}]},"category":[{"coding":[{"system":"http://hl7.org/fhir/us/core/CodeSystem/us-core-documentreference-category","code":"clinical-note","display":"Clinical Note"}]}],"subject":{"reference":"Patient/503d2fd5-b644-4d07-92a4-5f0d01e45cc8"},"date":"2020-11-29T03:16:17.629-05:00","author":[{"reference":"Practitioner/90c6c89d-c6b9-306d-b1ba-91dbf105a7ac","display":"Dr. Bobby524 Deckow585"}],"custodian":{"reference":"Organization/32836213-4ac7-3021-aad8-6383f3ced351","display":"PCP9022"},"content":[{"attachment":{"contentType":"text/plain","data":"CjIwMjAtMTEtMjkKCiMgQ2hpZWYgQ29tcGxhaW50Ck5vIGNvbXBsYWludHMuCgojIEhpc3Rvcnkgb2YgUHJlc2VudCBJbGxuZXNzClJveTM2NCBpcyBhIDE5IHllYXItb2xkIG5vbi1oaXNwYW5pYyB3aGl0ZSBtYWxlLgoKIyBTb2NpYWwgSGlzdG9yeQogUGF0aWVudCBpcyBhbiBhY3RpdmUgc21va2VyLiBQYXRpZW50IGlkZW50aWZpZXMgYXMgaGV0ZXJvc2V4dWFsLgoKUGF0aWVudCBjb21lcyBmcm9tIGEgaGlnaCBzb2Npb2Vjb25vbWljIGJhY2tncm91bmQuIFBhdGllbnQgaXMgYSBjb2xsZWdlIGdyYWR1YXRlLiBQYXRpZW50IGN1cnJlbnRseSBoYXMgQmx1ZSBDcm9zcyBCbHVlIFNoaWVsZC4KCiMgQWxsZXJnaWVzCk5vIEtub3duIEFsbGVyZ2llcy4KCiMgTWVkaWNhdGlvbnMKTm8gQWN0aXZlIE1lZGljYXRpb25zLgoKIyBBc3Nlc3NtZW50IGFuZCBQbGFuCgoKIyMgUGxhbgpQYXRpZW50IHdhcyBnaXZlbiB0aGUgZm9sbG93aW5nIGltbXVuaXphdGlvbnM6IGluZmx1ZW56YSwgc2Vhc29uYWwsIGluamVjdGFibGUsIHByZXNlcnZhdGl2ZSBmcmVlLiAK"},"format":{"system":"http://ihe.net/fhir/ValueSet/IHE.FormatCode.codesystem","code":"urn:ihe:iti:xds:2017:mimeTypeSufficient","display":"mimeType Sufficient"}}],"context":{"encounter":[{"reference":"Encounter/3a7643c0-8c94-410a-b1d1-558ca71d9241"}],"period":{"start":"2020-11-29T03:16:17-05:00","end":"2020-11-29T03:31:17-05:00"}}},"request":{"method":"POST","url":"DocumentReference"}},{"fullUrl":"Claim/db7a9649-e163-46f3-8548-629473807e63","resource":{"resourceType":"Claim","id":"db7a9649-e163-46f3-8548-629473807e63","identifier":[{"system":"https://github.com/synthetichealth/synthea","value":"4b557910-1da4-4db0-a0c0-9a45187cb787"}],"status":"active","type":{"coding":[{"system":"http://terminology.hl7.org/CodeSystem/claim-type","code":"institutional"}]},"use":"claim","patient":{"reference":"Patient/503d2fd5-b644-4d07-92a4-5f0d01e45cc8","display":"Roy364 Bernhard322"},"billablePeriod":{"start":"2020-11-29T03:16:17-05:00","end":"2020-11-29T03:31:17-05:00"},"created":"2020-11-29T03:31:17-05:00","provider":{"reference":"Organization/32836213-4ac7-3021-aad8-6383f3ced351","display":"PCP9022"},"priority":{"coding":[{"system":"http://terminology.hl7.org/CodeSystem/processpriority","code":"normal"}]},"facility":{"reference":"Location/463fc781-da4d-4a0b-b676-4e19ef375ae7","display":"PCP9022"},"supportingInfo":[{"sequence":1,"category":{"coding":[{"system":"http://terminology.hl7.org/CodeSystem/claiminformationcategory","code":"info"}]},"valueReference":{"reference":"Immunization/a824419d-8ffc-4776-817d-7e7c9d303b25"}}],"insurance":[{"sequence":1,"focal":true,"coverage":{"display":"Blue Cross Blue Shield"}}],"item":[{"sequence":1,"productOrService":{"coding":[{"system":"http://snomed.info/sct","code":"162673000","display":"General examination of patient (procedure)"}],"text":"General examination of patient (procedure)"},"encounter":[{"reference":"Encounter/3a7643c0-8c94-410a-b1d1-558ca71d9241"}]},{"sequence":2,"informationSequence":[1],"productOrService":{"coding":[{"system":"http://hl7.org/fhir/sid/cvx","code":"140","display":"Influenza, seasonal, injectable, preservative free"}],"text":"Influenza, seasonal, injectable, preservative free"},"net":{"value":140.52,"currency":"USD"}}],"total":{"value":129.16,"currency":"USD"}},"request":{"method":"POST","url":"Claim"}},{"fullUrl":"ExplanationOfBenefit/b85dee26-05fa-412f-a8c9-6dac85187fd2","resource":{"resourceType":"ExplanationOfBenefit","id":"b85dee26-05fa-412f-a8c9-6dac85187fd2","contained":[{"resourceType":"ServiceRequest","id":"referral","status":"completed","intent":"order","subject":{"reference":"Patient/503d2fd5-b644-4d07-92a4-5f0d01e45cc8"},"requester":{"reference":"Practitioner/90c6c89d-c6b9-306d-b1ba-91dbf105a7ac"},"performer":[{"reference":"Practitioner/90c6c89d-c6b9-306d-b1ba-91dbf105a7ac"}]},{"resourceType":"Coverage","id":"coverage","status":"active","type":{"text":"Blue Cross Blue Shield"},"beneficiary":{"reference":"Patient/503d2fd5-b644-4d07-92a4-5f0d01e45cc8"},"payor":[{"display":"Blue Cross Blue Shield"}]}],"identifier":[{"system":"https://github.com/synthetichealth/synthea","value":"69b09a94-6658-42ff-a4e5-3aca36ef18d2"},{"system":"https://bluebutton.cms.gov/resources/variables/clm_id","value":"db7a9649-e163-46f3-8548-629473807e63"},{"system":"https://bluebutton.cms.gov/resources/identifier/claim-group","value":"99999999999"}],"status":"active","type":{"coding":[{"system":"http://terminology.hl7.org/CodeSystem/claim-type","code":"institutional"}]},"use":"claim","patient":{"reference":"Patient/503d2fd5-b644-4d07-92a4-5f0d01e45cc8"},"billablePeriod":{"start":"2020-11-29T03:31:17-05:00","end":"2021-11-29T03:31:17-05:00"},"created":"2020-11-29T03:31:17-05:00","insurer":{"display":"Blue Cross Blue Shield"},"provider":{"reference":"Practitioner/90c6c89d-c6b9-306d-b1ba-91dbf105a7ac"},"referral":{"reference":"#referral"},"facility":{"reference":"Location/463fc781-da4d-4a0b-b676-4e19ef375ae7","display":"PCP9022"},"claim":{"reference":"Claim/db7a9649-e163-46f3-8548-629473807e63"},"outcome":"complete","careTeam":[{"sequence":1,"provider":{"reference":"Practitioner/90c6c89d-c6b9-306d-b1ba-91dbf105a7ac"},"role":{"coding":[{"system":"http://terminology.hl7.org/CodeSystem/claimcareteamrole","code":"primary","display":"Primary Care Practitioner"}]}}],"insurance":[{"focal":true,"coverage":{"reference":"#coverage","display":"Blue Cross Blue Shield"}}],"item":[{"sequence":1,"category":{"coding":[{"system":"https://bluebutton.cms.gov/resources/variables/line_cms_type_srvc_cd","code":"1","display":"Medical care"}]},"productOrService":{"coding":[{"system":"http://snomed.info/sct","code":"162673000","display":"General examination of patient (procedure)"}],"text":"General examination of patient (procedure)"},"servicedPeriod":{"start":"2020-11-29T03:16:17-05:00","end":"2020-11-29T03:31:17-05:00"},"locationCodeableConcept":{"coding":[{"system":"http://terminology.hl7.org/CodeSystem/ex-serviceplace","code":"19","display":"Off Campus-Outpatient Hospital"}]},"encounter":[{"reference":"Encounter/3a7643c0-8c94-410a-b1d1-558ca71d9241"}]},{"sequence":2,"informationSequence":[1],"category":{"coding":[{"system":"https://bluebutton.cms.gov/resources/variables/line_cms_type_srvc_cd","code":"1","display":"Medical care"}]},"productOrService":{"coding":[{"system":"http://hl7.org/fhir/sid/cvx","code":"140","display":"Influenza, seasonal, injectable, preservative free"}],"text":"Influenza, seasonal, injectable, preservative free"},"servicedPeriod":{"start":"2020-11-29T03:16:17-05:00","end":"2020-11-29T03:31:17-05:00"},"locationCodeableConcept":{"coding":[{"system":"http://terminology.hl7.org/CodeSystem/ex-serviceplace","code":"19","display":"Off Campus-Outpatient Hospital"}]},"net":{"value":140.52,"currency":"USD"},"adjudication":[{"category":{"coding":[{"system":"https://bluebutton.cms.gov/resources/codesystem/adjudication","code":"https://bluebutton.cms.gov/resources/variables/line_coinsrnc_amt","display":"Line Beneficiary Coinsurance Amount"}]},"amount":{"value":28.104000000000003,"currency":"USD"}},{"category":{"coding":[{"system":"https://bluebutton.cms.gov/resources/codesystem/adjudication","code":"https://bluebutton.cms.gov/resources/variables/line_prvdr_pmt_amt","display":"Line Provider Payment Amount"}]},"amount":{"value":112.41600000000001,"currency":"USD"}},{"category":{"coding":[{"system":"https://bluebutton.cms.gov/resources/codesystem/adjudication","code":"https://bluebutton.cms.gov/resources/variables/line_sbmtd_chrg_amt","display":"Line Submitted Charge Amount"}]},"amount":{"value":140.52,"currency":"USD"}},{"category":{"coding":[{"system":"https://bluebutton.cms.gov/resources/codesystem/adjudication","code":"https://bluebutton.cms.gov/resources/variables/line_alowd_chrg_amt","display":"Line Allowed Charge Amount"}]},"amount":{"value":140.52,"currency":"USD"}},{"category":{"coding":[{"system":"https://bluebutton.cms.gov/resources/codesystem/adjudication","code":"https://bluebutton.cms.gov/resources/variables/line_bene_ptb_ddctbl_amt","display":"Line Beneficiary Part B Deductible Amount"}]},"amount":{"value":0,"currency":"USD"}},{"category":{"coding":[{"system":"https://bluebutton.cms.gov/resources/codesystem/adjudication","code":"https://bluebutton.cms.gov/resources/variables/line_prcsg_ind_cd","display":"Line Processing Indicator Code"}]}}]}],"total":[{"category":{"coding":[{"system":"http://terminology.hl7.org/CodeSystem/adjudication","code":"submitted","display":"Submitted Amount"}],"text":"Submitted Amount"},"amount":{"value":129.16,"currency":"USD"}}],"payment":{"amount":{"value":112.41600000000001,"currency":"USD"}}},"request":{"method":"POST","url":"ExplanationOfBenefit"}},{"fullUrl":"Provenance/be5c87e6-da64-4bfa-8c74-7dbaa8243c07","resource":{"resourceType":"Provenance","id":"be5c87e6-da64-4bfa-8c74-7dbaa8243c07","meta":{"profile":["http://hl7.org/fhir/us/core/StructureDefinition/us-core-provenance"]},"target":[{"reference":"Patient/503d2fd5-b644-4d07-92a4-5f0d01e45cc8"},{"reference":"Location/463fc781-da4d-4a0b-b676-4e19ef375ae7"},{"reference":"Organization/32836213-4ac7-3021-aad8-6383f3ced351"},{"reference":"Practitioner/90c6c89d-c6b9-306d-b1ba-91dbf105a7ac"},{"reference":"PractitionerRole/e409617c-e023-44db-aa92-dc6824b5e30b"},{"reference":"Encounter/980912e0-553f-424c-8bb3-f942c8e5fb82"},{"reference":"Immunization/9bcf53ca-dae5-4baa-92d5-4fb4bd2a344c"},{"reference":"DiagnosticReport/acedfc92-e5fd-493e-be55-8d654ebd5958"},{"reference":"DocumentReference/7f8bebf4-c115-4185-be17-c1bcd6a4bbcb"},{"reference":"Claim/f3ee7f27-3df1-43cb-af1a-7f16a6f3a90b"},{"reference":"ExplanationOfBenefit/87530883-d30a-4238-ac37-e2f168df78e9"},{"reference":"Encounter/3a7643c0-8c94-410a-b1d1-558ca71d9241"},{"reference":"Immunization/a824419d-8ffc-4776-817d-7e7c9d303b25"},{"reference":"DiagnosticReport/08f07e04-ad66-4d78-894a-8e8f5235b9f5"},{"reference":"DocumentReference/0523af58-e929-45d9-9fdf-adb72e5c780f"},{"reference":"Claim/db7a9649-e163-46f3-8548-629473807e63"},{"reference":"ExplanationOfBenefit/b85dee26-05fa-412f-a8c9-6dac85187fd2"}],"recorded":"2021-05-16T04:16:17.629-04:00","agent":[{"type":{"coding":[{"system":"http://terminology.hl7.org/CodeSystem/provenance-participant-type","code":"author","display":"Author"}],"text":"Author"},"who":{"reference":"Practitioner/90c6c89d-c6b9-306d-b1ba-91dbf105a7ac","display":"Dr. Bobby524 Deckow585"},"onBehalfOf":{"reference":"Organization/32836213-4ac7-3021-aad8-6383f3ced351","display":"PCP9022"}},{"type":{"coding":[{"system":"http://hl7.org/fhir/us/core/CodeSystem/us-core-provenance-participant-type","code":"transmitter","display":"Transmitter"}],"text":"Transmitter"},"who":{"reference":"Practitioner/90c6c89d-c6b9-306d-b1ba-91dbf105a7ac","display":"Dr. Bobby524 Deckow585"},"onBehalfOf":{"reference":"Organization/32836213-4ac7-3021-aad8-6383f3ced351","display":"PCP9022"}}]},"request":{"method":"POST","url":"Provenance"}}]}